Workbook

Sheet Summary
B1: ETERNAL LIMITED (NSE: ETERNAL · BSE: 543320 · formerly Zomato Ltd)
B2: Date - March 2nd, 2026.
A4: # | B4: RATING | C4: BUY
B6: Current market price (2-Mar-2026) | C6: =Assumptions!$D$6 -> 242.87
B7: 12-month target price | C7: =ROUND(E21,0) -> 304
B8: Implied price upside | C8: =C7/C6-1 -> 0.25169844
B9: Forward dividend yield (no dividend declared) | C9: 0
B10: Implied total return | C10: =C8+C9 -> 0.25169844
B12: Market capitalisation (₹ cr) | C12: =Assumptions!$D$8 -> 234379.26
B13: Shares outstanding (crore) | C13: =Assumptions!$D$7 -> 965.04
B14: Net cash after lease liabilities, FY26E (₹ cr) | C14: =Model!E94 -> 18911.497
B15: Net cash as % of market capitalisation
A17: # | B17: VALUATION TRIANGULATION | C17: Value/share | D17: Weight | E17: Contribution
B18: Discounted cash flow (FCFF, 7-year explicit) | C18: =DCF!L40 -> 238.04632 | D18: 0.3 | E18: =C18*D18 -> 71.413896
B19: Sum-of-the-parts on FY30E segment metrics | C19: =SOTP!$D$24 -> 336.0702 | D19: 0.5 | E19: =C19*D19 -> 168.0351
B20: EV / net order value vs peer set (FY27E) | C20: =Comps!$D$22 -> 322.96112 | D20: 0.2 | E20: =C20*D20 -> 64.592223
B21: Blended fair value | D21: =SUM(D18:D20) -> 1 | E21: =SUM(E18:E20) -> 304.04122
B22: Probability-weighted scenario value | E22: =Scenarios!$G$41 -> 257.62968
A24: # | B24: KEY FINANCIALS (₹ cr) | C24: FY25A | D24: FY26E | E24: FY27E | F24: FY28E | G24: FY29E
B25: Net order value, B2C (₹ cr) | C25: =RevBuild!D43 -> 62290.985 | D25: =RevBuild!E43 -> 96765.787 | E25: =RevBuild!F43 -> 139409 | F25: =RevBuild!G43 -> 188619.07 | G25: =RevBuild!H43 -> 241983.28
B26: Revenue from operations (₹ cr) | C26: =Model!D7 -> 20241.73 | D26: =Model!E7 -> 54670.182 | E26: =Model!F7 -> 95618.265 | F26: =Model!G7 -> 134814.2 | G26: =Model!H7 -> 177601.87
B27: Adjusted EBITDA (₹ cr) | C27: =Model!D20 -> 765.94938 | D27: =Model!E20 -> 1152.5053 | E27: =Model!F20 -> 3985.0552 | F27: =Model!G20 -> 7655.4012 | G27: =Model!H20 -> 12016.294
B28: Adjusted EBITDA margin on NOV | C28: =Model!D20/RevBuild!D43 -> 0.012296312 | D28: =Model!E20/RevBuild!E43 -> 0.011910256 | E28: =Model!F20/RevBuild!F43 -> 0.028585351 | F28: =Model!G20/RevBuild!G43 -> 0.04058657 | G28: =Model!H20/RevBuild!H43 -> 0.049657539
B29: EBIT (₹ cr) | C29: =Model!D26 -> -225.19712 | D29: =Model!E26 -> -228.28574 | E29: =Model!F26 -> 2740.7282 | F29: =Model!G26 -> 6472.5325 | G29: =Model!H26 -> 10833.328
B30: PAT (₹ cr) | C30: =Model!D31 -> 527.53898 | D30: =Model!E31 -> 382.94396 | E30: =Model!F31 -> 2561.0468 | F30: =Model!G31 -> 5842.9716 | G30: =Model!H31 -> 9997.5864
B31: EPS (₹) | C31: =Model!D33 -> 0.60063643 | D31: =Model!E33 -> 0.39681668 | E31: =Model!F33 -> 2.6538245 | F31: =Model!G33 -> 6.0546419 | G31: =Model!H33 -> 10.359764
B32: EV / NOV (x) | C32: =(Assumptions!$D$8-Model!D94)/RevBuild!D43 -> 3.4927568 | D32: =(Assumptions!$D$8-Model!E94)/RevBuild!E43 -> 2.2266937 | E32: =(Assumptions!$D$8-Model!F94)/RevBuild!F43 -> 1.5276794 | F32: =(Assumptions!$D$8-Model!G94)/RevBuild!G43 -> 1.0986171 | G32: =(Assumptions!$D$8-Model!H94)/RevBuild!H43 -> 0.81410149
A34: # | B34: AUDIT CHECKS
B35: Balance sheet check, FY25A-FY33E (all must be zero) | C35: =Model!D56 -> 0 | D35: =Model!E56 -> 0 | E35: =Model!F56 -> 0 | F35: =Model!G56 -> 0 | G35: =Model!H56 -> 0 | H35: =Model!I56 -> 0 | I35: =Model!J56 -> 0 | J35: =Model!K56 -> 0 | K35: =Model!L56 -> 0
B36: Segment revenue build vs reported, FY25A (₹ cr) | C36: =RevBuild!D47 -> -1.2703323
B37: Q3FY26 segment NOV build vs disclosed B2C NOV (₹ cr) | C37: =Historicals!H51 -> -24.198582
B38: DuPont ROE vs direct ROE (must be zero) | C38: =Ratios!D21 -> 0 | D38: =Ratios!E21 -> 0 | E38: =Ratios!F21 -> 0 | F38: =Ratios!G21 -> 0 | G38: =Ratios!H21 -> 0 | H38: =Ratios!I21 -> 0 | I38: =Ratios!J21 -> 0 | J38: =Ratios!K21 -> 0 | K38: =Ratios!L21 -> 0
B39: Equity roll-forward vs balance sheet (must be zero) | D39: =Model!E64-Model!E54 -> 0 | E39: =Model!F64-Model!F54 -> 0 | F39: =Model!G64-Model!G54 -> 0 | G39: =Model!H64-Model!H54 -> 0 | H39: =Model!I64-Model!I54 -> 0 | I39: =Model!J64-Model!J54 -> 0 | J39: =Model!K64-Model!K54 -> 0 | K39: =Model!L64-Model!L54 -> 0
B40: Scenario probabilities sum to 100% | C40: =Scenarios!$F$42 -> 1
B41: FY26E closing cash vs disclosed 31-Dec-25 balance (₹ cr, informational) | C41: =Model!E36-Assumptions!$D$11 -> 5781.4966
B42: Historical balance sheet check, FY21A-FY25A (must be zero) | C42: =Historicals!C82 -> 0 | D42: =Historicals!D82 -> 1 | E42: =Historicals!E82 -> 0 | F42: =Historicals!F82 -> 0 | G42: =Historicals!G82 -> 0

Sheet Assumptions
B2: Assumptions & Drivers
A4: # | B4: Driver | C4: Units | D4: FY25A | E4: FY26E | F4: FY27E | G4: FY28E | H4: FY29E | I4: FY30E | J4: FY31E | K4: FY32E | L4: FY33E
B5: MARKET DATA (as at 2 March 2026; values in column C)
B6: Current market price (CMP) | C6: ₹/sh | D6: 242.87
B7: Shares outstanding | C7: crore | D7: 965.04
B8: Market capitalisation | C8: ₹ cr | D8: =$D$6*$D$7 -> 234379.26
B9: 52-week high / low | C9: ₹/sh | D9: 368.40 / 189.60
B10: 12-month target price | C10: ₹/sh | D10: =Summary!$C$7 -> 304
B11: Cash, deposits & treasury investments, 31-Dec-2025 | C11: ₹ cr | D11: 17820
A13: # | B13: QUICK COMMERCE (BLINKIT) - DARK-STORE ROLL-FORWARD
B14: Dark stores, closing | C14: count | D14: 1301 | E14: 2300 | F14: 3300 | G14: 4300 | H14: 5200 | I14: 6000 | J14: 6700 | K14: 7300 | L14: 7800
B15: Net order value per store per day | C15: ₹ lakh | D15: 6.71 | E15: 7.39 | F15: 7.9 | G15: 8.5 | H15: 9.15 | I15: 9.8 | J15: 10.4 | K15: 10.95 | L15: 11.45
B16: Revenue as % of NOV | C16: % | D16: 0.2327 | E16: 0.778 | F16: 0.92 | G16: 0.92 | H16: 0.92 | I16: 0.92 | J16: 0.92 | K16: 0.92 | L16: 0.92
B17: Adjusted EBITDA margin (% of NOV) | C17: % | D17: -0.0327 | E17: -0.006 | F17: 0.02 | G17: 0.034 | H17: 0.044 | I17: 0.051 | J17: 0.055 | K17: 0.058 | L17: 0.06
A19: # | B19: FOOD DELIVERY (ZOMATO)
B20: Net order value | C20: ₹ cr | D20: 33300 | E20: 38300
B21: NOV growth, YoY | C21: % | F21: 0.17 | G21: 0.17 | H21: 0.15 | I21: 0.13 | J21: 0.11 | K21: 0.1 | L21: 0.09
B22: Revenue as % of NOV | C22: % | D22: 0.24259 | E22: 0.265 | F22: 0.275 | G22: 0.28 | H22: 0.285 | I22: 0.29 | J22: 0.29 | K22: 0.29 | L22: 0.29
B23: Adjusted EBITDA margin (% of NOV) | C23: % | D23: 0.048 | E23: 0.053 | F23: 0.059 | G23: 0.064 | H23: 0.068 | I23: 0.071 | J23: 0.073 | K23: 0.074 | L23: 0.075
A25: # | B25: GOING-OUT (DISTRICT) AND HYPERPURE
B26: Going-out net order value | C26: ₹ cr | D26: 6618 | E26: 9900
B27: Going-out NOV growth, YoY | C27: % | F27: 0.4 | G27: 0.32 | H27: 0.26 | I27: 0.22 | J27: 0.18 | K27: 0.15 | L27: 0.12
B28: Going-out revenue as % of NOV | C28: % | D28: 0.1105 | E28: 0.115 | F28: 0.12 | G28: 0.125 | H28: 0.128 | I28: 0.13 | J28: 0.13 | K28: 0.13 | L28: 0.13
B29: Going-out adjusted EBITDA margin (% of NOV) | C29: % | D29: -0.005 | E29: -0.04 | F29: -0.01 | G29: 0.015 | H29: 0.03 | I29: 0.05 | J29: 0.055 | K29: 0.06 | L29: 0.06
B30: Hyperpure revenue | C30: ₹ cr | D30: 6196 | E30: 5558
B31: Hyperpure revenue growth, YoY | C31: % | F31: 0.26 | G31: 0.24 | H31: 0.2 | I31: 0.17 | J31: 0.14 | K31: 0.11 | L31: 0.09
B32: Hyperpure adjusted EBITDA margin (% of revenue) | C32: % | D32: -0.009 | E32: 0 | F32: 0.015 | G32: 0.025 | H32: 0.035 | I32: 0.04 | J32: 0.045 | K32: 0.045 | L32: 0.045
B33: Other segments revenue (Bistro, Nugget) | C33: ₹ cr | D33: 30 | E33: 40 | F33: 350 | G33: 700 | H33: 1100 | I33: 1500 | J33: 1900 | K33: 2200 | L33: 2500
B34: Other segments adjusted EBITDA | C34: ₹ cr | D34: -12 | E34: -190 | F34: -240 | G34: -200 | H34: -120 | I34: -50 | J34: 0 | K34: 50 | L34: 100
A36: # | B36: COST, CAPITAL AND WORKING-CAPITAL DRIVERS
B37: Share-based payment expense | C37: ₹ cr | D37: 698 | E37: 810 | F37: 860 | G37: 910 | H37: 960 | I37: 1010 | J37: 1060 | K37: 1110 | L37: 1160
B38: Lease rent paid, per average dark store | C38: ₹ cr | D38: 0.441 | E38: 0.459 | F38: 0.477 | G38: 0.496 | H38: 0.516 | I38: 0.537 | J38: 0.558 | K38: 0.581 | L38: 0.604
B39: Lease rent paid, offices & warehouses | C39: ₹ cr | D39: 167 | E39: 188 | F39: 195 | G39: 211 | H39: 228 | I39: 246 | J39: 266 | K39: 287 | L39: 310
B40: Lease liability per closing dark store | C40: ₹ cr | D40: 1.05 | E40: 1.72 | F40: 1.85 | G40: 1.85 | H40: 1.85 | I40: 1.85 | J40: 1.85 | K40: 1.85 | L40: 1.85
B41: Lease liability, non-store (offices, warehouses) | C41: ₹ cr | D41: 680 | E41: 734 | F41: 793 | G41: 856 | H41: 925 | I41: 999 | J41: 1079 | K41: 1165 | L41: 1258
B42: Lease interest rate | C42: % | D42: 0.11 | E42: 0.11 | F42: 0.11 | G42: 0.11 | H42: 0.11 | I42: 0.11 | J42: 0.11 | K42: 0.11 | L42: 0.11
B43: Capital expenditure per new dark store | C43: ₹ cr | D43: 0.71 | E43: 0.75 | F43: 0.8 | G43: 0.84 | H43: 0.89 | I43: 0.95 | J43: 1 | K43: 1.06 | L43: 1.13
B44: Warehousing capex, % of quick commerce NOV | C44: % | D44: 0.0035 | E44: 0.0035 | F44: 0.0035 | G44: 0.0035 | H44: 0.0035 | I44: 0.0035 | J44: 0.0035 | K44: 0.0035 | L44: 0.0035
B45: Technology & other capex, % of non-QC revenue | C45: % | D45: 0.02 | E45: 0.02 | F45: 0.02 | G45: 0.02 | H45: 0.02 | I45: 0.02 | J45: 0.02 | K45: 0.02 | L45: 0.02
B46: PP&E depreciation rate on average net block | C46: % | D46: 0.16 | E46: 0.16 | F46: 0.16 | G46: 0.16 | H46: 0.16 | I46: 0.16 | J46: 0.16 | K46: 0.16 | L46: 0.16
B47: Intangible amortisation | C47: ₹ cr | D47: 250 | E47: 260 | F47: 230 | G47: 200 | H47: 180 | I47: 165 | J47: 155 | K47: 150 | L47: 150
B48: Cost of goods sold, % of quick commerce revenue | C48: % | D48: 0 | E48: 0.704 | F48: 0.783 | G48: 0.783 | H48: 0.783 | I48: 0.783 | J48: 0.783 | K48: 0.783 | L48: 0.783
... B56: Effective tax rate | C56: % | D56: 0.244 | E56: 0.5 | F56: 0.32 | G56: 0.24 | H56: 0.2 | I56: 0.22 | J56: 0.2517 | K56: 0.2517 | L56: 0.2517
A58: # | B58: COST OF CAPITAL - see WACC tab
B59: WACC (base case) | C59: % | D59: =WACC!$D$29 -> 0.12660169
B60: Terminal growth rate (INR nominal) | C60: % | D60: 0.065

Sheet Historicals
A1: ADITYA NAIR RESEARCH
A2: Reported Historicals - Full Post-IPO History, FY21A to 9M FY26
A3: Ind AS consolidated, ₹ in crore. Zomato listed 23 July 2021; FY22 is the first annual report as a listed company and FY21 the prospectus comparative. Income statement, balance sheet, cash flow and derived trends - all reported. FY26E links live to the Model tab.
A5: Reported financials | B5: Units | C5: FY21A | D5: FY22A | E5: FY23A | F5: FY24A | G5: FY25A | H5: Q3FY26A | I5: 9MFY26A | J5: FY26E
A6: CONSOLIDATED INCOME STATEMENT (₹ cr)
A7: Revenue from operations | B7: ₹ cr | C7: 1994 | D7: 4192 | E7: 7079 | F7: 12114 | G7: 20243 | H7: 16315 | I7: 37072 | J7: =Model!E7 -> 54670.182
A8: YoY growth | B8: % | D8: =D7/C7-1 -> 1.1023069 | E8: =E7/D7-1 -> 0.68869275 | F8: =F7/E7-1 -> 0.71125865 | G8: =G7/F7-1 -> 0.67104177 | J8: =J7/G7-1 -> 1.7006957
A9: Other income (treasury & fair-value) | B9: ₹ cr | C9: -200 | D9: 793 | E9: 682 | F9: 846 | G9: 1077 | H9: 348 | I9: 1054 | J9: =Model!E28 -> 1364.5987
A10: Total income | B10: ₹ cr | C10: =C7+C9 -> 1794 | D10: =D7+D9 -> 4985 | E10: =E7+E9 -> 7761 | F10: =F7+F9 -> 12960 | G10: =G7+G9 -> 21320 | H10: =H7+H9 -> 16663 | I10: =I7+I9 -> 38126 | J10: =J7+J9 -> 56034.781
A11: Total operating expenditure | B11: ₹ cr | C11: -2461 | D11: -6043 | E11: -8290 | F11: -12071 | G11: -19606 | H11: -15947 | I11: -36350 | J11: =-(Model!E7-Model!E23) -> -53313.247
A12: EBITDA (operating profit, as reported) | B12: ₹ cr | C12: =C10-C9+C11 -> -467 | D12: =D10-D9+D11 -> -1851 | E12: =E10-E9+E11 -> -1211 | F12: =F10-F9+F11 -> 43 | G12: =G10-G9+G11 -> 637 | H12: =H10-H9+H11 -> 368 | I12: =I10-I9+I11 -> 722 | J12: =J10-J9+J11 -> 1356.9348
A13: EBITDA margin on revenue | B13: % | C13: =C12/C7 -> -0.23420261 | D13: =D12/D7 -> -0.44155534 | E13: =E12/E7 -> -0.17106936 | F13: =F12/F7 -> 0.003549612 | G13: =G12/G7 -> 0.031467668 | H13: =H12/H7 -> 0.02255593 | I13: =I12/I7 -> 0.019475615 | J13: =J12/J7 -> 0.024820382
A14: Finance costs | B14: ₹ cr | C14: -10 | D14: -12 | E14: -49 | F14: -72 | G14: -154 | H14: -106 | I14: -260 | J14: =Model!E29 -> -370.425
A15: Depreciation & amortisation | B15: ₹ cr | C15: -138 | D15: -150 | E15: -437 | F15: -526 | G15: -863 | H15: -439 | I15: -1129 | J15: =Model!E24 -> -1585.2205
A16: Profit before tax - as reported | B16: ₹ cr | C16: -815 | D16: -1220 | E16: -1015 | F16: 291 | G16: 697 | H16: 170 | I16: 387 | J16: =Model!E30 -> 765.88793
A17: Tax (expense) / credit | B17: ₹ cr | C17: -1 | D17: -2 | E17: 44 | F17: 60 | G17: -170 | H17: -68 | I17: -195 | J17: =-Model!E34 -> -382.94396
A18: Profit after tax | B18: ₹ cr | C18: -816 | D18: -1222 | E18: -971 | F18: 351 | G18: 527 | H18: 102 | I18: 192 | J18: =Model!E31 -> 382.94396
A19: EPS - basic (₹) | B19: ₹ | D19: -1.54 | E19: -1.14 | F19: 0.4 | G19: 0.55 | H19: 0.11 | I19: 0.21 | J19: =Model!E33 -> 0.39681668
A20: Arithmetic check: EBITDA + other income − finance − D&A vs reported PBT | C20: =C12+C9+C14+C15-C16 -> 0 | D20: =D12+D9+D14+D15-D16 -> 0 | E20: =E12+E9+E14+E15-E16 -> 0 | F20: =F12+F9+F14+F15-F16 -> 0 | G20: =G12+G9+G14+G15-G16 -> 0 | H20: =H12+H9+H14+H15-H16 -> 1 | I20: =I12+I9+I14+I15-I16 -> 0 | J20: =J12+J9+J14+J15-J16 -> 0
A22: OPERATING EXPENDITURE DETAIL - disclosed by line only from FY25A
A23: Purchases of stock-in-trade | B23: ₹ cr | G23: -5653 | H23: -10076 | I23: -21428
A24: Cost of materials consumed | B24: ₹ cr | G24: 0 | H24: -15 | I24: -15
A25: Changes in inventories | B25: ₹ cr | G25: 88 | H25: 290 | I25: 1616
A26: Employee benefits expense | B26: ₹ cr | G26: -2558 | H26: -914 | I26: -2609
A27: Advertisement & sales promotion | B27: ₹ cr | G27: -1972 | H27: -937 | I27: -2414
A28: Delivery & related charges | B28: ₹ cr | G28: -5728 | H28: -2376 | I28: -6458
A29: Other expenses | B29: ₹ cr | G29: -3783 | H29: -1919 | I29: -5042
A30: Total per expense detail | B30: ₹ cr | G30: =SUM(G23:G29) -> -19606 | H30: =SUM(H23:H29) -> -15947 | I30: =SUM(I23:I29) -> -36350
A31: Check vs total operating expenditure (row 11) | G31: =G30-G11 -> 0 | H31: =H30-H11 -> 0 | I31: =I30-I11 -> 0
A33: SEGMENT REVENUE FROM EXTERNAL CUSTOMERS (₹ cr)
A34: India food ordering & delivery | B34: ₹ cr | G34: 8080 | H34: 2676 | I34: 7422
A35: Quick commerce (Blinkit) | B35: ₹ cr | G35: 5206 | H35: 12256 | I35: 24547
A36: Hyperpure supplies (B2B) | B36: ₹ cr | G36: 6196 | H36: 1070 | I36: 4388
A37: Going-out (District) | B37: ₹ cr | G37: 731 | H37: 300 | I37: 692
A38: All other segments (residual) | B38: ₹ cr | G38: 30 | H38: 13 | I38: 23
A39: Total segment revenue | B39: ₹ cr | G39: =SUM(G34:G38) -> 20243 | H39: =SUM(H34:H38) -> 16315 | I39: =SUM(I34:I38) -> 37072
A40: Cross-check vs reported revenue (must be zero) | G40: =G39-G7 -> 0 | H40: =H39-H7 -> 0 | I40: =I39-I7 -> 0
A42: ADJUSTED EBITDA BY SEGMENT AND THE B2C NOV BUILD (₹ cr) - Q3 FY26
A43: Adjusted EBITDA - food delivery | B43: ₹ cr | H43: 531
A44: Adjusted EBITDA - quick commerce | B44: ₹ cr | H44: 4
A45: Adjusted EBITDA - going-out | B45: ₹ cr | H45: -121
A46: Adjusted EBITDA - Hyperpure | B46: ₹ cr | H46: 1
A47: Adjusted EBITDA - other segments | B47: ₹ cr | H47: -51
A48: Consolidated adjusted EBITDA (disclosed ₹364cr) | B48: ₹ cr | H48: =SUM(H43:H47) -> 364
A49: Implied NOV - food delivery (₹531cr ÷ 5.4%) | B49: ₹ cr | H49: =H43/0.054 -> 9833.3333
A50: Implied NOV - going-out (₹121cr ÷ 4.7%) | B50: ₹ cr | H50: =-H45/0.047 -> 2574.4681
A51: NOV build vs disclosed B2C NOV of ₹25,732cr | H51: =H49+13300+H50-25732 -> -24.198582
A53: OPERATING METRICS - THE TELL
A54: Blinkit dark stores, period end | F54: 526 | G54: 1301 | H54: 2,027 | I54: 2,027
A55: Net new dark stores added in period | G55: 775 | H55: 211 | I55: 726
A56: Blinkit NOV | G56: 22,371 | H56: 13,300 | I56: 34,182
A57: Blinkit NOV growth YoY | G57: 113% | H57: 121% | I57: 128%
A58: Blinkit NOV per store per day (₹ lakh, derived) | G58: 6.71 | H58: 7.52 | I58: 7.52
A59: Share of Blinkit NOV on own inventory | H59: ~90%
A60: Food delivery NOV growth YoY | H60: 16.6%
A61: Food delivery GOV growth YoY | H61: 21.3%
A62: Food delivery adj. EBITDA margin on NOV | H62: 5.4%
A63: Blinkit adj. EBITDA margin on NOV | H63: 0.0%
A64: India quick commerce NOV share - Blinkit | H64: 48%
A65: India QC NOV share - Instamart / Zepto | H65: 24% / 22%
A67: CONSOLIDATED BALANCE SHEET (₹ cr) - as reported
A68: Line | B68: Units | C68: FY21A | D68: FY22A | E68: FY23A | F68: FY24A | G68: FY25A
A69: Equity share capital | B69: ₹ cr | C69: 0 | D69: 764 | E69: 836 | F69: 868 | G69: 907
A70: Other equity (reserves & surplus) | B70: ₹ cr | C70: 7644 | D70: 15741 | E70: 18624 | F70: 19545 | G70: 29410
A71: TOTAL EQUITY | B71: ₹ cr | C71: =C69+C70 -> 7644 | D71: =D69+D70 -> 16505 | E71: =E69+E70 -> 19460 | F71: =F69+F70 -> 20413 | G71: =G69+G70 -> 30317
A72: Lease liabilities & borrowings | B72: ₹ cr | C72: 527 | D72: 70 | E72: 507 | F72: 749 | G72: 2045
A73: Other liabilities (payables, provisions, other) | B73: ₹ cr | C73: 532 | D73: 751 | E73: 1632 | F73: 2194 | G73: 3261
A74: TOTAL LIABILITIES | B74: ₹ cr | C74: =C72+C73 -> 1059 | D74: =D72+D73 -> 821 | E74: =E72+E73 -> 2139 | F74: =F72+F73 -> 2943 | G74: =G72+G73 -> 5306
A75: TOTAL EQUITY & LIABILITIES | B75: ₹ cr | C75: =C71+C74 -> 8703 | D75: =D71+D74 -> 17326 | E75: =E71+E74 -> 21599 | F75: =F71+F74 -> 23356 | G75: =G71+G74 -> 35623
A77: Fixed assets (PP&E, ROU, goodwill, intangibles) | B77: ₹ cr | C77: 1539 | D77: 1404 | E77: 6344 | F77: 6448 | G77: 9532
A78: Capital work in progress | B78: ₹ cr | C78: 0 | D78: 1 | E78: 7 | F78: 18 | G78: 51
A79: Investments (treasury portfolio) | B79: ₹ cr | C79: 2205 | D79: 4718 | E79: 6765 | F79: 11645 | G79: 13192
A80: Other assets (cash, inventory, receivables, other) | B80: ₹ cr | C80: 4959 | D80: 11204 | E80: 8483 | F80: 5245 | G80: 12848
A81: TOTAL ASSETS | B81: ₹ cr | C81: =SUM(C77:C80) -> 8703 | D81: =SUM(D77:D80) -> 17327 | E81: =SUM(E77:E80) -> 21599 | F81: =SUM(F77:F80) -> 23356 | G81: =SUM(G77:G80) -> 35623
A82: Balance check (must be zero) | C82: =C81-C75 -> 0 | D82: =D81-D75 -> 1 | E82: =E81-E75 -> 0 | F82: =F81-F75 -> 0 | G82: =G81-G75 -> 0
A83: Memo: net cash & investments | B83: ₹ cr | C83: =C79+C80-C73 -> 6632 | D83: =D79+D80-D73 -> 15171 | E83: =E79+E80-E73 -> 13616 | F83: =F79+F80-F73 -> 14696 | G83: =G79+G80-G73 -> 22779
A85: CONSOLIDATED CASH FLOW STATEMENT (₹ cr) - as reported
A86: Line | B86: Units | C86: FY21A | D86: FY22A | E86: FY23A | F86: FY24A | G86: FY25A
A87: Cash from operating activities | B87: ₹ cr | C87: -1018 | D87: -693 | E87: -844 | F87: 646 | G87: 308
A88: Cash from investing activities | B88: ₹ cr | C88: -5245 | D88: -7971 | E88: 797 | F88: -348 | G88: -7993
A89: Cash from financing activities | B89: ₹ cr | C89: 6402 | D89: 8750 | E89: -127 | F89: -207 | G89: 8042
A90: Net change in cash | B90: ₹ cr | C90: =SUM(C87:C89) -> 139 | D90: =SUM(D87:D89) -> 86 | E90: =SUM(E87:E89) -> -174 | F90: =SUM(F87:F89) -> 91 | G90: =SUM(G87:G89) -> 357
A91: Free cash flow (CFO less capex) | B91: ₹ cr | C91: -1028 | D91: -750 | E91: -945 | F91: 444 | G91: -623
A92: Implied capital expenditure | B92: ₹ cr | C92: =C87-C91 -> 10 | D92: =D87-D91 -> 57 | E92: =E87-E91 -> 101 | F92: =F87-F91 -> 202 | G92: =G87-G91 -> 931
A93: Operating cash flow as % of EBITDA | B93: % | F93: =F87/F12 -> 15.023256 | G93: =G87/G12 -> 0.48351648
A95: DERIVED WORKING-CAPITAL AND RETURN TRENDS - why the long history matters
A96: Ratio | B96: Units | C96: FY21A | D96: FY22A | E96: FY23A | F96: FY24A | G96: FY25A
A97: Inventory days | B97: days | C97: 28 | D97: 28 | E97: 22 | F97: 11 | G97: 12
A98: Debtor days | B98: days | C98: 24 | D98: 14 | E98: 24 | F98: 24 | G98: 35
A99: Days payable | B99: days | C99: 565 | D99: 298 | E99: 178 | F99: 112 | G99: 101
A100: Cash conversion cycle | B100: days | C100: =C97+C98-C99 -> -513 | D100: =D97+D98-D99 -> -256 | E100: =E97+E98-E99 -> -132 | F100: =F97+F98-F99 -> -77 | G100: =G97+G98-G99 -> -54
A101: Working capital days | B101: days | C101: 96 | D101: 316 | E101: 200 | F101: 41 | G101: 45
A102: Capex as % of revenue | B102: % | C102: =C92/C7 -> 0.0050150451 | D102: =D92/D7 -> 0.013597328 | E102: =E92/E7 -> 0.014267552 | F102: =F92/F7 -> 0.016674922 | G102: =G92/G7 -> 0.045991207
A103: Return on capital employed | B103: % | C103: -0.12 | D103: -0.13 | E103: -0.06 | F103: 0.01 | G103: 0.03
A104: Revenue growth, YoY | B104: % | D104: =D7/C7-1 -> 1.1023069 | E104: =E7/D7-1 -> 0.68869275 | F104: =F7/E7-1 -> 0.71125865 | G104: =G7/F7-1 -> 0.67104177
A105: Memo: model's forecast cash conversion cycle, FY27E | B105: days | G105: =Ratios!F34 -> -8

Sheet RevBuild
B2: Revenue Build - Segment NOV and Unit Economics
B3: Bottom-up build: dark-store roll-forward × NOV per store per day for quick commerce; NOV growth × monetisation for the consumer platforms. ₹ in crore.
A5: # | B5: Segment build | C5: Units | D5: FY25A | E5: FY26E | F5: FY27E | G5: FY28E | H5: FY29E | I5: FY30E | J5: FY31E | K5: FY32E | L5: FY33E
B6: QUICK COMMERCE (BLINKIT) - DARK-STORE ROLL-FORWARD
B7: Dark stores, opening | C7: count | D7: 526 | E7: =D9 -> 1301 | F7: =E9 -> 2300 | G7: =F9 -> 3300 | H7: =G9 -> 4300 | I7: =H9 -> 5200 | J7: =I9 -> 6000 | K7: =J9 -> 6700 | L7: =K9 -> 7300
B8: Net new stores added | C8: count | D8: =D9-D7 -> 775 | E8: =E9-E7 -> 999 | F8: =F9-F7 -> 1000 | G8: =G9-G7 -> 1000 | H8: =H9-H7 -> 900 | I8: =I9-I7 -> 800 | J8: =J9-J7 -> 700 | K8: =K9-K7 -> 600 | L8: =L9-L7 -> 500
B9: Dark stores, closing | C9: count | D9: =Assumptions!D14 -> 1301 | E9: =Assumptions!E14 -> 2300 | F9: =Assumptions!F14 -> 3300 | G9: =Assumptions!G14 -> 4300 | H9: =Assumptions!H14 -> 5200 | I9: =Assumptions!I14 -> 6000 | J9: =Assumptions!J14 -> 6700 | K9: =Assumptions!K14 -> 7300 | L9: =Assumptions!L14 -> 7800
B10: Average stores in operation | C10: count | D10: =(D7+D9)/2 -> 913.5 | E10: =(E7+E9)/2 -> 1800.5 | F10: =(F7+F9)/2 -> 2800 | G10: =(G7+G9)/2 -> 3800 | H10: =(H7+H9)/2 -> 4750 | I10: =(I7+I9)/2 -> 5600 | J10: =(J7+J9)/2 -> 6350 | K10: =(K7+K9)/2 -> 7000 | L10: =(L7+L9)/2 -> 7550
B11: NOV per store per day | C11: ₹ lakh | D11: =Assumptions!D15 -> 6.71 | E11: =Assumptions!E15 -> 7.39 | F11: =Assumptions!F15 -> 7.9 | G11: =Assumptions!G15 -> 8.5 | H11: =Assumptions!H15 -> 9.15 | I11: =Assumptions!I15 -> 9.8 | J11: =Assumptions!J15 -> 10.4 | K11: =Assumptions!K15 -> 10.95 | L11: =Assumptions!L15 -> 11.45
B12: Quick commerce net order value | C12: ₹ cr | D12: =D10*365*D11/100 -> 22372.985 | E12: =E10*365*E11/100 -> 48565.787 | F12: =F10*365*F11/100 -> 80738 | G12: =G10*365*G11/100 -> 117895 | H12: =H10*365*H11/100 -> 158638.12 | I12: =I10*365*I11/100 -> 200312 | J12: =J10*365*J11/100 -> 241046 | K12: =K10*365*K11/100 -> 279772.5 | L12: =L10*365*L11/100 -> 315533.37
B13: YoY growth | C13: % | E13: =E12/D12-1 -> 1.1707334 | F13: =F12/E12-1 -> 0.66244604 | G13: =G12/F12-1 -> 0.460217 | H13: =H12/G12-1 -> 0.34558824 | I13: =I12/H12-1 -> 0.26269773 | J13: =J12/I12-1 -> 0.20335277 | K13: =K12/J12-1 -> 0.16066021 | L13: =L12/K12-1 -> 0.12782127
B14: Revenue as % of NOV | C14: % | D14: =Assumptions!D16 -> 0.2327 | E14: =Assumptions!E16 -> 0.778 | F14: =Assumptions!F16 -> 0.92 | G14: =Assumptions!G16 -> 0.92 | H14: =Assumptions!H16 -> 0.92 | I14: =Assumptions!I16 -> 0.92 | J14: =Assumptions!J16 -> 0.92 | K14: =Assumptions!K16 -> 0.92 | L14: =Assumptions!L16 -> 0.92
B15: Quick commerce revenue | C15: ₹ cr | D15: =D12*D14 -> 5206.1937 | E15: =E12*E14 -> 37784.182 | F15: =F12*F14 -> 74278.96 | G15: =G12*G14 -> 108463.4 | H15: =H12*H14 -> 145947.08 | I15: =I12*I14 -> 184287.04 | J15: =J12*J14 -> 221762.32 | K15: =K12*K14 -> 257390.7 | L15: =L12*L14 -> 290290.7
B16: Adjusted EBITDA margin (% of NOV) | C16: % | D16: =Assumptions!D17 -> -0.0327 | E16: =Assumptions!E17 -> -0.006 | F16: =Assumptions!F17 -> 0.02 | G16: =Assumptions!G17 -> 0.034 | H16: =Assumptions!H17 -> 0.044 | I16: =Assumptions!I17 -> 0.051 | J16: =Assumptions!J17 -> 0.055 | K16: =Assumptions!K17 -> 0.058 | L16: =Assumptions!L17 -> 0.06
B17: Quick commerce adjusted EBITDA | C17: ₹ cr | D17: =D12*D16 -> -731.59662 | E17: =E12*E16 -> -291.39472 | F17: =F12*F16 -> 1614.76 | G17: =G12*G16 -> 4008.43 | H17: =H12*H16 -> 6980.0775 | I17: =I12*I16 -> 10215.912 | J17: =J12*J16 -> 13257.53 | K17: =K12*K16 -> 16226.805 | L17: =L12*L16 -> 18932.002
A19: # | B19: FOOD DELIVERY (ZOMATO)
B20: Food delivery net order value | C20: ₹ cr | D20: =Assumptions!D20 -> 33300 | E20: =Assumptions!E20 -> 38300 | F20: =E20*(1+Assumptions!F21) -> 44811 | G20: =F20*(1+Assumptions!G21) -> 52428.87 | H20: =G20*(1+Assumptions!H21) -> 60293.2 | I20: =H20*(1+Assumptions!I21) -> 68131.317 | J20: =I20*(1+Assumptions!J21) -> 75625.761 | K20: =J20*(1+Assumptions!K21) -> 83188.338 | L20: =K20*(1+Assumptions!L21) -> 90675.288
B21: YoY growth | C21: % | E21: =E20/D20-1 -> 0.15015015 | F21: =F20/E20-1 -> 0.17 | G21: =G20/F20-1 -> 0.17 | H21: =H20/G20-1 -> 0.15 | I21: =I20/H20-1 -> 0.13 | J21: =J20/I20-1 -> 0.11 | K21: =K20/J20-1 -> 0.1 | L21: =L20/K20-1 -> 0.09
B22: Revenue as % of NOV | C22: % | D22: =Assumptions!D22 -> 0.24259 | E22: =Assumptions!E22 -> 0.265 | F22: =Assumptions!F22 -> 0.275 | G22: =Assumptions!G22 -> 0.28 | H22: =Assumptions!H22 -> 0.285 | I22: =Assumptions!I22 -> 0.29 | J22: =Assumptions!J22 -> 0.29 | K22: =Assumptions!K22 -> 0.29 | L22: =Assumptions!L22 -> 0.29
B23: Food delivery revenue | C23: ₹ cr | D23: =D20*D22 -> 8078.247 | E23: =E20*E22 -> 10149.5 | F23: =F20*F22 -> 12323.025 | G23: =G20*G22 -> 14680.084 | H23: =H20*H22 -> 17183.562 | I23: =I20*I22 -> 19758.082 | J23: =J20*J22 -> 21931.471 | K23: =K20*K22 -> 24124.618 | L23: =L20*L22 -> 26295.833
B24: Adjusted EBITDA margin (% of NOV) | C24: % | D24: =Assumptions!D23 -> 0.048 | E24: =Assumptions!E23 -> 0.053 | F24: =Assumptions!F23 -> 0.059 | G24: =Assumptions!G23 -> 0.064 | H24: =Assumptions!H23 -> 0.068 | I24: =Assumptions!I23 -> 0.071 | J24: =Assumptions!J23 -> 0.073 | K24: =Assumptions!K23 -> 0.074 | L24: =Assumptions!L23 -> 0.075
B25: Food delivery adjusted EBITDA | C25: ₹ cr | D25: =D20*D24 -> 1598.4 | E25: =E20*E24 -> 2029.9 | F25: =F20*F24 -> 2643.849 | G25: =G20*G24 -> 3355.4477 | H25: =H20*H24 -> 4099.9376 | I25: =I20*I24 -> 4837.3235 | J25: =J20*J24 -> 5520.6806 | K25: =K20*K24 -> 6155.937 | L25: =L20*L24 -> 6800.6466
A27: # | B27: GOING-OUT (DISTRICT), HYPERPURE AND OTHER SEGMENTS
B28: Going-out net order value | C28: ₹ cr | D28: =Assumptions!D26 -> 6618 | E28: =Assumptions!E26 -> 9900 | F28: =E28*(1+Assumptions!F27) -> 13860 | G28: =F28*(1+Assumptions!G27) -> 18295.2 | H28: =G28*(1+Assumptions!H27) -> 23051.952 | I28: =H28*(1+Assumptions!I27) -> 28123.381 | J28: =I28*(1+Assumptions!J27) -> 33185.59 | K28: =J28*(1+Assumptions!K27) -> 38163.429 | L28: =K28*(1+Assumptions!L27) -> 42743.04
B29: Going-out revenue | C29: ₹ cr | D29: =D28*Assumptions!D28 -> 731.289 | E29: =E28*Assumptions!E28 -> 1138.5 | F29: =F28*Assumptions!F28 -> 1663.2 | G29: =G28*Assumptions!G28 -> 2286.9 | H29: =H28*Assumptions!H28 -> 2950.6499 | I29: =I28*Assumptions!I28 -> 3656.0396 | J29: =J28*Assumptions!J28 -> 4314.1267 | K29: =K28*Assumptions!K28 -> 4961.2457 | L29: =L28*Assumptions!L28 -> 5556.5952
B30: Going-out adjusted EBITDA | C30: ₹ cr | D30: =D28*Assumptions!D29 -> -33.09 | E30: =E28*Assumptions!E29 -> -396 | F30: =F28*Assumptions!F29 -> -138.6 | G30: =G28*Assumptions!G29 -> 274.428 | H30: =H28*Assumptions!H29 -> 691.55856 | I30: =I28*Assumptions!I29 -> 1406.1691 | J30: =J28*Assumptions!J29 -> 1825.2075 | K30: =K28*Assumptions!K29 -> 2289.8057 | L30: =L28*Assumptions!L29 -> 2564.5824
B31: Hyperpure revenue | C31: ₹ cr | D31: =Assumptions!D30 -> 6196 | E31: =Assumptions!E30 -> 5558 | F31: =E31*(1+Assumptions!F31) -> 7003.08 | G31: =F31*(1+Assumptions!G31) -> 8683.8192 | H31: =G31*(1+Assumptions!H31) -> 10420.583 | I31: =H31*(1+Assumptions!I31) -> 12192.082 | J31: =I31*(1+Assumptions!J31) -> 13898.974 | K31: =J31*(1+Assumptions!K31) -> 15427.861 | L31: =K31*(1+Assumptions!L31) -> 16816.368
B32: Hyperpure adjusted EBITDA | C32: ₹ cr | D32: =D31*Assumptions!D32 -> -55.764 | E32: =E31*Assumptions!E32 -> 0 | F32: =F31*Assumptions!F32 -> 105.0462 | G32: =G31*Assumptions!G32 -> 217.09548 | H32: =H31*Assumptions!H32 -> 364.72041 | I32: =I31*Assumptions!I32 -> 487.68329 | J32: =J31*Assumptions!J32 -> 625.45381 | K32: =K31*Assumptions!K32 -> 694.25373 | L32: =L31*Assumptions!L32 -> 756.73657
B33: Other segments revenue | C33: ₹ cr | D33: =Assumptions!D33 -> 30 | E33: =Assumptions!E33 -> 40 | F33: =Assumptions!F33 -> 350 | G33: =Assumptions!G33 -> 700 | H33: =Assumptions!H33 -> 1100 | I33: =Assumptions!I33 -> 1500 | J33: =Assumptions!J33 -> 1900 | K33: =Assumptions!K33 -> 2200 | L33: =Assumptions!L33 -> 2500
B34: Other segments adjusted EBITDA | C34: ₹ cr | D34: =Assumptions!D34 -> -12 | E34: =Assumptions!E34 -> -190 | F34: =Assumptions!F34 -> -240 | G34: =Assumptions!G34 -> -200 | H34: =Assumptions!H34 -> -120 | I34: =Assumptions!I34 -> -50 | J34: =Assumptions!J34 -> 0 | K34: =Assumptions!K34 -> 50 | L34: =Assumptions!L34 -> 100
A36: # | B36: CONSOLIDATED ROLL-UP
B37: Quick commerce revenue | D37: =D15 -> 5206.1937 | E37: =E15 -> 37784.182 | F37: =F15 -> 74278.96 | G37: =G15 -> 108463.4 | H37: =H15 -> 145947.08 | I37: =I15 -> 184287.04 | J37: =J15 -> 221762.32 | K37: =K15 -> 257390.7 | L37: =L15 -> 290290.7
B38: Food delivery revenue | D38: =D23 -> 8078.247 | E38: =E23 -> 10149.5 | F38: =F23 -> 12323.025 | G38: =G23 -> 14680.084 | H38: =H23 -> 17183.562 | I38: =I23 -> 19758.082 | J38: =J23 -> 21931.471 | K38: =K23 -> 24124.618 | L38: =L23 -> 26295.833
B39: Hyperpure revenue | D39: =D31 -> 6196 | E39: =E31 -> 5558 | F39: =F31 -> 7003.08 | G39: =G31 -> 8683.8192 | H39: =H31 -> 10420.583 | I39: =I31 -> 12192.082 | J39: =J31 -> 13898.974 | K39: =K31 -> 15427.861 | L39: =L31 -> 16816.368
B40: Going-out revenue | D40: =D29 -> 731.289 | E40: =E29 -> 1138.5 | F40: =F29 -> 1663.2 | G40: =G29 -> 2286.9 | H40: =H29 -> 2950.6499 | I40: =I29 -> 3656.0396 | J40: =J29 -> 4314.1267 | K40: =K29 -> 4961.2457 | L40: =L29 -> 5556.5952
B41: Other segments revenue | D41: =D33 -> 30 | E41: =E33 -> 40 | F41: =F33 -> 350 | G41: =G33 -> 700 | H41: =H33 -> 1100 | I41: =I33 -> 1500 | J41: =J33 -> 1900 | K41: =K33 -> 2200 | L41: =L33 -> 2500
B42: TOTAL REVENUE FROM OPERATIONS | D42: =SUM(D37:D41) -> 20241.73 | E42: =SUM(E37:E41) -> 54670.182 | F42: =SUM(F37:F41) -> 95618.265 | G42: =SUM(G37:G41) -> 134814.2 | H42: =SUM(H37:H41) -> 177601.87 | I42: =SUM(I37:I41) -> 221393.24 | J42: =SUM(J37:J41) -> 263806.89 | K42: =SUM(K37:K41) -> 304104.42 | L42: =SUM(L37:L41) -> 341459.5
B43: Net order value - B2C businesses | D43: =D12+D20+D28 -> 62290.985 | E43: =E12+E20+E28 -> 96765.787 | F43: =F12+F20+F28 -> 139409 | G43: =G12+G20+G28 -> 188619.07 | H43: =H12+H20+H28 -> 241983.28 | I43: =I12+I20+I28 -> 296566.7 | J43: =J12+J20+J28 -> 349857.35 | K43: =K12+K20+K28 -> 401124.27 | L43: =L12+L20+L28 -> 448951.7
B44: B2C NOV growth, YoY | E44: =E43/D43-1 -> 0.55344768 | F44: =F43/E43-1 -> 0.44068482 | G44: =G43/F43-1 -> 0.35299062 | H44: =H43/G43-1 -> 0.28292053 | I44: =I43/H43-1 -> 0.22556691 | J44: =J43/I43-1 -> 0.17969197 | K44: =K43/J43-1 -> 0.14653662 | L44: =L43/K43-1 -> 0.11923347
B45: CONSOLIDATED ADJUSTED EBITDA | D45: =D17+D25+D30+D32+D34 -> 765.94938 | E45: =E17+E25+E30+E32+E34 -> 1152.5053 | F45: =F17+F25+F30+F32+F34 -> 3985.0552 | G45: =G17+G25+G30+G32+G34 -> 7655.4012 | H45: =H17+H25+H30+H32+H34 -> 12016.294 | I45: =I17+I25+I30+I32+I34 -> 16897.088 | J45: =J17+J25+J30+J32+J34 -> 21228.872 | K45: =K17+K25+K30+K32+K34 -> 25416.801 | L45: =L17+L25+L30+L32+L34 -> 29153.968
B46: Cross-check vs reported FY25A revenue | D46: 20243
B47: Difference (must be ~0) | D47: =D42-D46 -> -1.2703323
B48: Memo: adjusted revenue (reported × 1.023) | D48: =D42*1.023 -> 20707.289 | E48: =E42*1.023 -> 55927.596 | F48: =F42*1.023 -> 97817.485 | G48: =G42*1.023 -> 137914.93 | H48: =H42*1.023 -> 181686.71 | I48: =I42*1.023 -> 226485.29 | J48: =J42*1.023 -> 269874.45 | K48: =K42*1.023 -> 311098.83 | L48: =L42*1.023 -> 349313.07

Sheet Model
B2: Three-Statement Model - Income Statement, Balance Sheet, Cash Flow
B3: ₹ in crore. FY25A is audited Ind AS. FY26E is nine months reported plus an estimated Q4. FY27E-FY33E are driven entirely from the Assumptions tab. Balance check must read zero in every period.
A5: # | B5: Consolidated financials | C5: Units | D5: FY25A | E5: FY26E | F5: FY27E | G5: FY28E | H5: FY29E | I5: FY30E | J5: FY31E | K5: FY32E | L5: FY33E
A6: # | B6: INCOME STATEMENT
B7: Revenue from operations | C7: ₹ cr | D7: =RevBuild!D42 -> 20241.73 | E7: =RevBuild!E42 -> 54670.182 | F7: =RevBuild!F42 -> 95618.265 | G7: =RevBuild!G42 -> 134814.2 | H7: =RevBuild!H42 -> 177601.87 | I7: =RevBuild!I42 -> 221393.24 | J7: =RevBuild!J42 -> 263806.89 | K7: =RevBuild!K42 -> 304104.42 | L7: =RevBuild!L42 -> 341459.5
B8: YoY growth | C8: % | E8: =E7/D7-1 -> 1.7008651 | F8: =F7/E7-1 -> 0.74900213 | G8: =G7/F7-1 -> 0.40992103 | H8: =H7/G7-1 -> 0.31738249 | I8: =I7/H7-1 -> 0.24657045 | J8: =J7/I7-1 -> 0.19157607 | K8: =K7/J7-1 -> 0.15275391 | L8: =L7/K7-1 -> 0.12283635
B9: Cost of goods sold | C9: ₹ cr | D9: =-(RevBuild!D15*Assumptions!D48+RevBuild!D31*Assumptions!D49) -> -5452.48 | E9: =-(RevBuild!E15*Assumptions!E48+RevBuild!E31*Assumptions!E49) -> -31491.104 | F9: =-(RevBuild!F15*Assumptions!F48+RevBuild!F31*Assumptions!F49) -> -64323.136 | G9: =-(RevBuild!G15*Assumptions!G48+RevBuild!G31*Assumptions!G49) -> -92568.603 | H9: =-(RevBuild!H15*Assumptions!H48+RevBuild!H31*Assumptions!H49) -> -123446.67 | I9: =-(RevBuild!I15*Assumptions!I48+RevBuild!I31*Assumptions!I49) -> -155025.78 | J9: =-(RevBuild!J15*Assumptions!J48+RevBuild!J31*Assumptions!J49) -> -185870.99 | K9: =-(RevBuild!K15*Assumptions!K48+RevBuild!K31*Assumptions!K49) -> -215113.44 | L9: =-(RevBuild!L15*Assumptions!L48+RevBuild!L31*Assumptions!L49) -> -242096.03
B10: Gross profit | D10: =D7+D9 -> 14789.25 | E10: =E7+E9 -> 23179.078 | F10: =F7+F9 -> 31295.129 | G10: =G7+G9 -> 42245.6 | H10: =H7+H9 -> 54155.197 | I10: =I7+I9 -> 66367.459 | J10: =J7+J9 -> 77935.898 | K10: =K7+K9 -> 88990.989 | L10: =L7+L9 -> 99363.476
B11: Gross margin | D11: =D10/D7 -> 0.73063172 | E11: =E10/E7 -> 0.42398026 | F11: =F10/F7 -> 0.32729237 | G11: =G10/G7 -> 0.31336164 | H11: =H10/H7 -> 0.3049247 | I11: =I10/I7 -> 0.29977184 | J11: =J10/J7 -> 0.29542783 | K11: =K10/K7 -> 0.292633 | L11: =L10/L7 -> 0.29099637
A13: # | B13: ADJUSTED EBITDA BRIDGE TO IND AS EBITDA
B14: Food delivery | C14: ₹ cr | D14: =RevBuild!D25 -> 1598.4 | E14: =RevBuild!E25 -> 2029.9 | F14: =RevBuild!F25 -> 2643.849 | G14: =RevBuild!G25 -> 3355.4477 | H14: =RevBuild!H25 -> 4099.9376 | I14: =RevBuild!I25 -> 4837.3235 | J14: =RevBuild!J25 -> 5520.6806 | K14: =RevBuild!K25 -> 6155.937 | L14: =RevBuild!L25 -> 6800.6466
B15: Quick commerce (Blinkit) | C15: ₹ cr | D15: =RevBuild!D17 -> -731.59662 | E15: =RevBuild!E17 -> -291.39472 | F15: =RevBuild!F17 -> 1614.76 | G15: =RevBuild!G17 -> 4008.43 | H15: =RevBuild!H17 -> 6980.0775 | I15: =RevBuild!I17 -> 10215.912 | J15: =RevBuild!J17 -> 13257.53 | K15: =RevBuild!K17 -> 16226.805 | L15: =RevBuild!L17 -> 18932.002
B16: Going-out (District) | C16: ₹ cr | D16: =RevBuild!D30 -> -33.09 | E16: =RevBuild!E30 -> -396 | F16: =RevBuild!F30 -> -138.6 | G16: =RevBuild!G30 -> 274.428 | H16: =RevBuild!H30 -> 691.55856 | I16: =RevBuild!I30 -> 1406.1691 | J16: =RevBuild!J30 -> 1825.2075 | K16: =RevBuild!K30 -> 2289.8057 | L16: =RevBuild!L30 -> 2564.5824
B17: Hyperpure | C17: ₹ cr | D17: =RevBuild!D32 -> -55.764 | E17: =RevBuild!E32 -> 0 | F17: =RevBuild!F32 -> 105.0462 | G17: =RevBuild!G32 -> 217.09548 | H17: =RevBuild!H32 -> 364.72041 | I17: =RevBuild!I32 -> 487.68329 | J17: =RevBuild!J32 -> 625.45381 | K17: =RevBuild!K32 -> 694.25373 | L17: =RevBuild!L32 -> 756.73657
B18: Other segments | C18: ₹ cr | D18: =RevBuild!D34 -> -12 | E18: =RevBuild!E34 -> -190 | F18: =RevBuild!F34 -> -240 | G18: =RevBuild!G34 -> -200 | H18: =RevBuild!H34 -> -120 | I18: =RevBuild!I34 -> -50 | J18: =RevBuild!J34 -> 0 | K18: =RevBuild!K34 -> 50 | L18: =RevBuild!L34 -> 100
A20: # | B20: ADJUSTED EBITDA | C20: ₹ cr | D20: =SUM(D14:D18) -> 765.94938 | E20: =SUM(E14:E18) -> 1152.5053 | F20: =SUM(F14:F18) -> 3985.0552 | G20: =SUM(G14:G18) -> 7655.4012 | H20: =SUM(H14:H18) -> 12016.294 | I20: =SUM(I14:I18) -> 16897.088 | J20: =SUM(J14:J18) -> 21228.872 | K20: =SUM(K14:K18) -> 25416.801 | L20: =SUM(L14:L18) -> 29153.968
B21: Less: share-based payment expense (added back in adj. EBITDA) | D21: =-Assumptions!D37 -> -698 | E21: =-Assumptions!E37 -> -810 | F21: =-Assumptions!F37 -> -860 | G21: =-Assumptions!G37 -> -910 | H21: =-Assumptions!H37 -> -960 | I21: =-Assumptions!I37 -> -1010 | J21: =-Assumptions!J37 -> -1060 | K21: =-Assumptions!K37 -> -1110 | L21: =-Assumptions!L37 -> -1160
B22: Add back: Ind AS 116 lease rent paid (charged in adj. EBITDA) | D22: =D88 -> 569.8535 | E22: =E88 -> 1014.4295 | F22: =F88 -> 1530.6 | G22: =G88 -> 2095.8 | H22: =H88 -> 2679 | I22: =I88 -> 3253.2 | J22: =J88 -> 3809.3 | K22: =K88 -> 4354 | L22: =L88 -> 4870.2
A23: # | B23: EBITDA (Ind AS reported basis) | D23: =D20+D21+D22 -> 637.80288 | E23: =E20+E21+E22 -> 1356.9348 | F23: =F20+F21+F22 -> 4655.6552 | G23: =G20+G21+G22 -> 8841.2012 | H23: =H20+H21+H22 -> 13735.294 | I23: =I20+I21+I22 -> 19140.288 | J23: =J20+J21+J22 -> 23978.172 | K23: =K20+K21+K22 -> 28660.801 | L23: =L20+L21+L22 -> 32864.168
B24: Depreciation & amortisation | C24: ₹ cr | D24: =-(D92+D93+Assumptions!D47) -> -863 | E24: =-(E92+E93+Assumptions!E47) -> -1585.2205 | F24: =-(F92+F93+Assumptions!F47) -> -1914.927 | G24: =-(G92+G93+Assumptions!G47) -> -2368.6687 | H24: =-(H92+H93+Assumptions!H47) -> -2901.9657 | I24: =-(I92+I93+Assumptions!I47) -> -3453.1381 | J24: =-(J92+J93+Assumptions!J47) -> -4010.7532 | K24: =-(K92+K93+Assumptions!K47) -> -4577.4458 | L24: =-(L92+L93+Assumptions!L47) -> -5133.8389
B25: of which: right-of-use depreciation | D25: =-D92 -> -420 | E25: =-E92 -> -1040.5045 | F25: =-F92 -> -1224.46 | G25: =-G92 -> -1518.755 | H25: =-H92 -> -1874.52 | I25: =-I92 -> -2240.88 | J25: =-J92 -> -2609.035 | K25: =-K92 -> -2985.48 | L25: =-L92 -> -3353.21
B26: EBIT | C26: ₹ cr | D26: =D23+D24 -> -225.19712 | E26: =E23+E24 -> -228.28574 | F26: =F23+F24 -> 2740.7282 | G26: =G23+G24 -> 6472.5325 | H26: =H23+H24 -> 10833.328 | I26: =I23+I24 -> 15687.15 | J26: =J23+J24 -> 19967.419 | K26: =K23+K24 -> 24083.356 | L26: =L23+L24 -> 27730.329
B27: EBIT margin on revenue | D27: =D26/D7 -> -0.011125389 | E27: =E26/E7 -> -0.0041756901 | F27: =F26/F7 -> 0.028663229 | G27: =G26/G7 -> 0.048010761 | H27: =H26/H7 -> 0.060997828 | I27: =I26/I7 -> 0.070856497 | J27: =J26/J7 -> 0.075689526 | K27: =K26/K7 -> 0.079194361 | L27: =L26/L7 -> 0.08121118
B28: Other income (treasury) | C28: ₹ cr | D28: 1077 | E28: =E96*Assumptions!E55 -> 1364.5987 | F28: =F96*Assumptions!F55 -> 1662.8571 | G28: =G96*Assumptions!G55 -> 2079.5831 | H28: =H96*Assumptions!H55 -> 2728.2346 | I28: =I96*Assumptions!I55 -> 3668.6778 | J28: =J96*Assumptions!J55 -> 4871.3638 | K28: =K96*Assumptions!K55 -> 6327.0487 | L28: =L96*Assumptions!L55 -> 8053.7143
B29: Finance costs (lease interest) | C29: ₹ cr | D29: =-D89 -> -154 | E29: =-E89 -> -370.425 | F29: =-F89 -> -637.34 | G29: =-G89 -> -863.995 | H29: =-H89 -> -1064.58 | I29: =-I89 -> -1245.42 | J29: =-J89 -> -1406.515 | K29: =-K89 -> -1547.92 | L29: =-L89 -> -1669.69
B30: Profit before tax | D30: =D26+D28+D29 -> 697.80288 | E30: =E26+E28+E29 -> 765.88793 | F30: =F26+F28+F29 -> 3766.2453 | G30: =G26+G28+G29 -> 7688.1205 | H30: =H26+H28+H29 -> 12496.983 | I30: =I26+I28+I29 -> 18110.408 | J30: =J26+J28+J29 -> 23432.267 | K30: =K26+K28+K29 -> 28862.484 | L30: =L26+L28+L29 -> 34114.353
B31: Profit after tax | D31: =D30*(1-Assumptions!D56) -> 527.53898 | E31: =E30*(1-Assumptions!E56) -> 382.94396 | F31: =F30*(1-Assumptions!F56) -> 2561.0468 | G31: =G30*(1-Assumptions!G56) -> 5842.9716 | H31: =H30*(1-Assumptions!H56) -> 9997.5864 | I31: =I30*(1-Assumptions!I56) -> 14126.118 | J31: =J30*(1-Assumptions!J56) -> 17534.366 | K31: =K30*(1-Assumptions!K56) -> 21597.797 | L31: =L30*(1-Assumptions!L56) -> 25527.771
B32: Weighted average shares outstanding | C32: crore | D32: 878.3 | E32: =Assumptions!$D$7 -> 965.04 | F32: =Assumptions!$D$7 -> 965.04 | G32: =Assumptions!$D$7 -> 965.04 | H32: =Assumptions!$D$7 -> 965.04 | I32: =Assumptions!$D$7 -> 965.04 | J32: =Assumptions!$D$7 -> 965.04 | K32: =Assumptions!$D$7 -> 965.04 | L32: =Assumptions!$D$7 -> 965.04
B33: EPS - basic | C33: ₹ | D33: =D31/D32 -> 0.60063643 | E33: =E31/E32 -> 0.39681668 | F33: =F31/F32 -> 2.6538245 | G33: =G31/G32 -> 6.0546419 | H33: =H31/H32 -> 10.359764 | I33: =I31/I32 -> 14.637857 | J33: =J31/J32 -> 18.169574 | K33: =K31/K32 -> 22.380209 | L33: =L31/L32 -> 26.452552
B34: Memo: tax expense | D34: =D30-D31 -> 170.2639 | E34: =E30-E31 -> 382.94396 | F34: =F30-F31 -> 1205.1985 | G34: =G30-G31 -> 1845.1489 | H34: =H30-H31 -> 2499.3966 | I34: =I30-I31 -> 3984.2897 | J34: =J30-J31 -> 5897.9017 | K34: =K30-K31 -> 7264.6873 | L34: =L30-L31 -> 8586.5828
A35: # | B35: BALANCE SHEET - ASSETS
B36: Cash, deposits & treasury investments | C36: ₹ cr | D36: 18857 | E36: =E84 -> 23601.497 | F36: =F84 -> 28305.004 | G36: =G84 -> 35970.137 | H36: =H84 -> 47925.317 | I36: =I84 -> 64041.797 | J36: =J84 -> 83554.493 | K36: =K84 -> 107091.73 | L36: =L84 -> 134504.8
B37: Inventories | D37: 665 | E37: =-E9*Assumptions!E50/365 -> 1207.878 | F37: =-F9*Assumptions!F50/365 -> 2467.1888 | G37: =-G9*Assumptions!G50/365 -> 3550.5766 | H37: =-H9*Assumptions!H50/365 -> 4734.9409 | I37: =-I9*Assumptions!I50/365 -> 5946.1945 | J37: =-J9*Assumptions!J50/365 -> 7129.2984 | K37: =-K9*Assumptions!K50/365 -> 8250.9263 | L37: =-L9*Assumptions!L50/365 -> 9285.875
B38: Trade receivables | D38: 1941 | E38: =E7*Assumptions!E52/365 -> 1198.2506 | F38: =F7*Assumptions!F52/365 -> 2095.7428 | G38: =G7*Assumptions!G52/365 -> 2954.8318 | H38: =H7*Assumptions!H52/365 -> 3892.6437 | I38: =I7*Assumptions!I52/365 -> 4852.4547 | J38: =J7*Assumptions!J52/365 -> 5782.0688 | K38: =K7*Assumptions!K52/365 -> 6665.3025 | L38: =L7*Assumptions!L52/365 -> 7484.0439
B39: Other current assets | D39: 2300 | E39: =E7*Assumptions!E53 -> 2186.8073 | F39: =F7*Assumptions!F53 -> 3824.7306 | G39: =G7*Assumptions!G53 -> 5392.5681 | H39: =H7*Assumptions!H53 -> 7104.0748 | I39: =I7*Assumptions!I53 -> 8855.7297 | J39: =J7*Assumptions!J53 -> 10552.276 | K39: =K7*Assumptions!K53 -> 12164.177 | L39: =L7*Assumptions!L53 -> 13658.38
B40: Property, plant & equipment, net | D40: 1151 | E40: =D40+E78*-1-E93 -> 2123.2342 | F40: =E40+F78*-1-F93 -> 3172.1363 | G40: =F40+G78*-1-G93 -> 4301.8712 | H40: =G40+H78*-1-H93 -> 5443.7548 | I40: =H40+I78*-1-I93 -> 6599.7128 | J40: =I40+J78*-1-J93 -> 7737.547 | K40: =J40+K78*-1-K93 -> 8845.0594 | L40: =K40+L78*-1-L93 -> 9907.1733
B41: Right-of-use assets | D41: 1738 | E41: =E50*0.85 -> 3986.5 | F41: =F50*0.85 -> 5863.3 | G41: =G50*0.85 -> 7489.35 | H41: =H50*0.85 -> 8963.25 | I41: =I50*0.85 -> 10284.15 | J41: =J50*0.85 -> 11452.9 | K41: =K50*0.85 -> 12469.5 | L41: =L50*0.85 -> 13334.8
B42: Goodwill (held flat) | D42: 5800 | E42: =D42 -> 5800 | F42: =E42 -> 5800 | G42: =F42 -> 5800 | H42: =G42 -> 5800 | I42: =H42 -> 5800 | J42: =I42 -> 5800 | K42: =J42 -> 5800 | L42: =K42 -> 5800
B43: Other intangible assets | D43: 1150 | E43: =D43-Assumptions!E47 -> 890 | F43: =E43-Assumptions!F47 -> 660 | G43: =F43-Assumptions!G47 -> 460 | H43: =G43-Assumptions!H47 -> 280 | I43: =H43-Assumptions!I47 -> 115 | J43: =I43-Assumptions!J47 -> -40 | K43: =J43-Assumptions!K47 -> -190 | L43: =K43-Assumptions!L47 -> -340
B44: Other non-current assets (held flat) | D44: 2021 | E44: =D44 -> 2021 | F44: =E44 -> 2021 | G44: =F44 -> 2021 | H44: =G44 -> 2021 | I44: =H44 -> 2021 | J44: =I44 -> 2021 | K44: =J44 -> 2021 | L44: =K44 -> 2021
B45: TOTAL ASSETS | D45: =SUM(D36:D44) -> 35623 | E45: =SUM(E36:E44) -> 43015.167 | F45: =SUM(F36:F44) -> 54209.102 | G45: =SUM(G36:G44) -> 67940.335 | H45: =SUM(H36:H44) -> 86164.981 | I45: =SUM(I36:I44) -> 108516.04 | J45: =SUM(J36:J44) -> 133989.58 | K45: =SUM(K36:K44) -> 163117.7 | L45: =SUM(L36:L44) -> 195656.07
A47: # | B47: BALANCE SHEET - LIABILITIES & EQUITY
B48: Trade payables | C48: ₹ cr | D48: 1564 | E48: =-E9*Assumptions!E51/365 -> 2588.3099 | F48: =-F9*Assumptions!F51/365 -> 5286.8331 | G48: =-G9*Assumptions!G51/365 -> 7608.3783 | H48: =-H9*Assumptions!H51/365 -> 10146.302 | I48: =-I9*Assumptions!I51/365 -> 12741.845 | J48: =-J9*Assumptions!J51/365 -> 15277.068 | K48: =-K9*Assumptions!K51/365 -> 17680.556 | L48: =-L9*Assumptions!L51/365 -> 19898.304
B49: Other current liabilities | D49: 1297 | E49: =E7*Assumptions!E54 -> 3826.9127 | F49: =F7*Assumptions!F54 -> 6693.2786 | G49: =G7*Assumptions!G54 -> 9436.9942 | H49: =H7*Assumptions!H54 -> 12432.131 | I49: =I7*Assumptions!I54 -> 15497.527 | J49: =J7*Assumptions!J54 -> 18466.482 | K49: =K7*Assumptions!K54 -> 21287.31 | L49: =L7*Assumptions!L54 -> 23902.165
B50: Lease liabilities | D50: 2045 | E50: =RevBuild!E9*Assumptions!E40+Assumptions!E41 -> 4690 | F50: =RevBuild!F9*Assumptions!F40+Assumptions!F41 -> 6898 | G50: =RevBuild!G9*Assumptions!G40+Assumptions!G41 -> 8811 | H50: =RevBuild!H9*Assumptions!H40+Assumptions!H41 -> 10545 | I50: =RevBuild!I9*Assumptions!I40+Assumptions!I41 -> 12099 | J50: =RevBuild!J9*Assumptions!J40+Assumptions!J41 -> 13474 | K50: =RevBuild!K9*Assumptions!K40+Assumptions!K41 -> 14670 | L50: =RevBuild!L9*Assumptions!L40+Assumptions!L41 -> 15688
B51: Other non-current liabilities (held flat) | D51: 400 | E51: =D51 -> 400 | F51: =E51 -> 400 | G51: =F51 -> 400 | H51: =G51 -> 400 | I51: =H51 -> 400 | J51: =I51 -> 400 | K51: =J51 -> 400 | L51: =K51 -> 400
B52: TOTAL LIABILITIES | D52: =SUM(D48:D51) -> 5306 | E52: =SUM(E48:E51) -> 11505.223 | F52: =SUM(F48:F51) -> 19278.112 | G52: =SUM(G48:G51) -> 26256.373 | H52: =SUM(H48:H51) -> 33523.433 | I52: =SUM(I48:I51) -> 40738.372 | J52: =SUM(J48:J51) -> 47617.55 | K52: =SUM(K48:K51) -> 54037.866 | L52: =SUM(L48:L51) -> 59888.469
B54: Total equity | D54: 30317 | E54: =E64 -> 31509.944 | F54: =F64 -> 34930.991 | G54: =G64 -> 41683.962 | H54: =H64 -> 52641.549 | I54: =I64 -> 67777.667 | J54: =J64 -> 86372.032 | K54: =K64 -> 109079.83 | L54: =L64 -> 135767.6
B55: TOTAL LIABILITIES & EQUITY | D55: =D52+D54 -> 35623 | E55: =E52+E54 -> 43015.167 | F55: =F52+F54 -> 54209.102 | G55: =G52+G54 -> 67940.335 | H55: =H52+H54 -> 86164.981 | I55: =I52+I54 -> 108516.04 | J55: =J52+J54 -> 133989.58 | K55: =K52+K54 -> 163117.7 | L55: =L52+L54 -> 195656.07
B56: BALANCE CHECK (must be zero) | D56: =D45-D55 -> 0 | E56: =E45-E55 -> 0 | F56: =F45-F55 -> 0 | G56: =G45-G55 -> 0 | H56: =H45-H55 -> 0 | I56: =I45-I55 -> 0 | J56: =J45-J55 -> 0 | K56: =K45-K55 -> 0 | L56: =L45-L55 -> 0
A58: # | B58: EQUITY ROLL-FORWARD
B59: Opening equity | E59: =D54 -> 30317 | F59: =E54 -> 31509.944 | G59: =F54 -> 34930.991 | H59: =G54 -> 41683.962 | I59: =H54 -> 52641.549 | J59: =I54 -> 67777.667 | K59: =J54 -> 86372.032 | L59: =K54 -> 109079.83
B60: Profit after tax | E60: =E31 -> 382.94396 | F60: =F31 -> 2561.0468 | G60: =G31 -> 5842.9716 | H60: =H31 -> 9997.5864 | I60: =I31 -> 14126.118 | J60: =J31 -> 17534.366 | K60: =K31 -> 21597.797 | L60: =L31 -> 25527.771
B61: Share-based payment credited to reserves | E61: =Assumptions!E37 -> 810 | F61: =Assumptions!F37 -> 860 | G61: =Assumptions!G37 -> 910 | H61: =Assumptions!H37 -> 960 | I61: =Assumptions!I37 -> 1010 | J61: =Assumptions!J37 -> 1060 | K61: =Assumptions!K37 -> 1110 | L61: =Assumptions!L37 -> 1160
B62: Dividends paid (none declared) | E62: 0 | F62: 0 | G62: 0 | H62: 0 | I62: 0 | J62: 0 | K62: 0 | L62: 0
B63: Other comprehensive income (set to nil) | E63: 0 | F63: 0 | G63: 0 | H63: 0 | I63: 0 | J63: 0 | K63: 0 | L63: 0
B64: Closing equity (check vs balance sheet) | E64: =SUM(E59:E63) -> 31509.944 | F64: =SUM(F59:F63) -> 34930.991 | G64: =SUM(G59:G63) -> 41683.962 | H64: =SUM(H59:H63) -> 52641.549 | I64: =SUM(I59:I63) -> 67777.667 | J64: =SUM(J59:J63) -> 86372.032 | K64: =SUM(K59:K63) -> 109079.83 | L64: =SUM(L59:L63) -> 135767.6
A66: # | B66: CASH FLOW STATEMENT
B67: Profit after tax | E67: =E31 -> 382.94396 | F67: =F31 -> 2561.0468 | G67: =G31 -> 5842.9716 | H67: =H31 -> 9997.5864 | I67: =I31 -> 14126.118 | J67: =J31 -> 17534.366 | K67: =K31 -> 21597.797 | L67: =L31 -> 25527.771
B68: Depreciation & amortisation | E68: =-E24 -> 1585.2205 | F68: =-F24 -> 1914.927 | G68: =-G24 -> 2368.6687 | H68: =-H24 -> 2901.9657 | I68: =-I24 -> 3453.1381 | J68: =-J24 -> 4010.7532 | K68: =-K24 -> 4577.4458 | L68: =-L24 -> 5133.8389
B69: Share-based payment expense | E69: =Assumptions!E37 -> 810 | F69: =Assumptions!F37 -> 860 | G69: =Assumptions!G37 -> 910 | H69: =Assumptions!H37 -> 960 | I69: =Assumptions!I37 -> 1010 | J69: =Assumptions!J37 -> 1060 | K69: =Assumptions!K37 -> 1110 | L69: =Assumptions!L37 -> 1160
B70: (Increase) / decrease in inventories | E70: =-(E37-D37) -> -542.87797 | F70: =-(F37-E37) -> -1259.3108 | G70: =-(G37-F37) -> -1083.3878 | H70: =-(H37-G37) -> -1184.3643 | I70: =-(I37-H37) -> -1211.2536 | J70: =-(J37-I37) -> -1183.1039 | K70: =-(K37-J37) -> -1121.6279 | L70: =-(L37-K37) -> -1034.9487
B71: (Increase) / decrease in receivables | E71: =-(E38-D38) -> 742.74943 | F71: =-(F38-E38) -> -897.49223 | G71: =-(G38-F38) -> -859.08905 | H71: =-(H38-G38) -> -937.81188 | I71: =-(I38-H38) -> -959.81093 | J71: =-(J38-I38) -> -929.61419 | K71: =-(K38-J38) -> -883.2336 | L71: =-(L38-K38) -> -818.74143
B72: (Increase) / decrease in other current assets | E72: =-(E39-D39) -> 113.19272 | F72: =-(F39-E39) -> -1637.9233 | G72: =-(G39-F39) -> -1567.8375 | H72: =-(H39-G39) -> -1711.5067 | I72: =-(I39-H39) -> -1751.6549 | J72: =-(J39-I39) -> -1696.5459 | K72: =-(K39-J39) -> -1611.9013 | L72: =-(L39-K39) -> -1494.2031
B73: (Increase) / decrease in other non-current assets | E73: =-(E44-D44) -> 0 | F73: =-(F44-E44) -> 0 | G73: =-(G44-F44) -> 0 | H73: =-(H44-G44) -> 0 | I73: =-(I44-H44) -> 0 | J73: =-(J44-I44) -> 0 | K73: =-(K44-J44) -> 0 | L73: =-(L44-K44) -> 0
B74: Increase / (decrease) in trade payables | E74: =E48-D48 -> 1024.3099 | F74: =F48-E48 -> 2698.5232 | G74: =G48-F48 -> 2321.5452 | H74: =H48-G48 -> 2537.9235 | I74: =I48-H48 -> 2595.5434 | J74: =J48-I48 -> 2535.2226 | K74: =K48-J48 -> 2403.4884 | L74: =L48-K48 -> 2217.7472
B75: Increase / (decrease) in other current liabilities | E75: =E49-D49 -> 2529.9127 | F75: =F49-E49 -> 2866.3658 | G75: =G49-F49 -> 2743.7156 | H75: =H49-G49 -> 2995.1367 | I75: =I49-H49 -> 3065.3961 | J75: =J49-I49 -> 2968.9553 | K75: =K49-J49 -> 2820.8273 | L75: =L49-K49 -> 2614.8554
B76: Increase / (decrease) in other non-current liabilities | E76: =E51-D51 -> 0 | F76: =F51-E51 -> 0 | G76: =G51-F51 -> 0 | H76: =H51-G51 -> 0 | I76: =I51-H51 -> 0 | J76: =J51-I51 -> 0 | K76: =K51-J51 -> 0 | L76: =L51-K51 -> 0
B77: Net cash from operating activities | E77: =SUM(E67:E76) -> 6645.4513 | F77: =SUM(F67:F76) -> 7106.1364 | G77: =SUM(G67:G76) -> 10676.587 | H77: =SUM(H67:H76) -> 15558.929 | I77: =SUM(I67:I76) -> 20327.476 | J77: =SUM(J67:J76) -> 24300.033 | K77: =SUM(K67:K76) -> 28892.796 | L77: =SUM(L67:L76) -> 33306.319
B78: Capital expenditure | E78: =-(RevBuild!E8*Assumptions!E43+RevBuild!E12*Assumptions!E44+(RevBuild!E23+RevBuild!E29+RevBuild!E31+RevBuild!E33)*Assumptions!E45) -> -1256.9503 | F78: =-(RevBuild!F8*Assumptions!F43+RevBuild!F12*Assumptions!F44+(RevBuild!F23+RevBuild!F29+RevBuild!F31+RevBuild!F33)*Assumptions!F45) -> -1509.3691 | G78: =-(RevBuild!G8*Assumptions!G43+RevBuild!G12*Assumptions!G44+(RevBuild!G23+RevBuild!G29+RevBuild!G31+RevBuild!G33)*Assumptions!G45) -> -1779.6486 | H78: =-(RevBuild!H8*Assumptions!H43+RevBuild!H12*Assumptions!H44+(RevBuild!H23+RevBuild!H29+RevBuild!H31+RevBuild!H33)*Assumptions!H45) -> -1989.3293 | I78: =-(RevBuild!I8*Assumptions!I43+RevBuild!I12*Assumptions!I44+(RevBuild!I23+RevBuild!I29+RevBuild!I31+RevBuild!I33)*Assumptions!I45) -> -2203.2161 | J78: =-(RevBuild!J8*Assumptions!J43+RevBuild!J12*Assumptions!J44+(RevBuild!J23+RevBuild!J29+RevBuild!J31+RevBuild!J33)*Assumptions!J45) -> -2384.5524 | K78: =-(RevBuild!K8*Assumptions!K43+RevBuild!K12*Assumptions!K44+(RevBuild!K23+RevBuild!K29+RevBuild!K31+RevBuild!K33)*Assumptions!K45) -> -2549.4782 | L78: =-(RevBuild!L8*Assumptions!L43+RevBuild!L12*Assumptions!L44+(RevBuild!L23+RevBuild!L29+RevBuild!L31+RevBuild!L33)*Assumptions!L45) -> -2692.7428
B79: Net cash used in investing activities | E79: =E78 -> -1256.9503 | F79: =F78 -> -1509.3691 | G79: =G78 -> -1779.6486 | H79: =H78 -> -1989.3293 | I79: =I78 -> -2203.2161 | J79: =J78 -> -2384.5524 | K79: =K78 -> -2549.4782 | L79: =L78 -> -2692.7428
B80: Lease principal repayments | E80: =-E90 -> -644.0045 | F80: =-F90 -> -893.26 | G80: =-G90 -> -1231.805 | H80: =-H90 -> -1614.42 | I80: =-I90 -> -2007.78 | J80: =-J90 -> -2402.785 | K80: =-K90 -> -2806.08 | L80: =-L90 -> -3200.51
B81: Net cash from financing activities | E81: =E80 -> -644.0045 | F81: =F80 -> -893.26 | G81: =G80 -> -1231.805 | H81: =H80 -> -1614.42 | I81: =I80 -> -2007.78 | J81: =J80 -> -2402.785 | K81: =K80 -> -2806.08 | L81: =L80 -> -3200.51
B82: Net change in cash & investments | E82: =E77+E79+E81 -> 4744.4966 | F82: =F77+F79+F81 -> 4703.5073 | G82: =G77+G79+G81 -> 7665.1333 | H82: =H77+H79+H81 -> 11955.18 | I82: =I77+I79+I81 -> 16116.48 | J82: =J77+J79+J81 -> 19512.695 | K82: =K77+K79+K81 -> 23537.237 | L82: =L77+L79+L81 -> 27413.066
B83: Opening cash & investments | E83: =D36 -> 18857 | F83: =E36 -> 23601.497 | G83: =F36 -> 28305.004 | H83: =G36 -> 35970.137 | I83: =H36 -> 47925.317 | J83: =I36 -> 64041.797 | K83: =J36 -> 83554.493 | L83: =K36 -> 107091.73
B84: Closing cash & investments | E84: =E82+E83 -> 23601.497 | F84: =F82+F83 -> 28305.004 | G84: =G82+G83 -> 35970.137 | H84: =H82+H83 -> 47925.317 | I84: =I82+I83 -> 64041.797 | J84: =J82+J83 -> 83554.493 | K84: =K82+K83 -> 107091.73 | L84: =L82+L83 -> 134504.8
B85: Memo: free cash flow (CFO less capex) | E85: =E77+E78 -> 5388.5011 | F85: =F77+F78 -> 5596.7673 | G85: =G77+G78 -> 8896.9383 | H85: =H77+H78 -> 13569.6 | I85: =I77+I78 -> 18124.26 | J85: =J77+J78 -> 21915.48 | K85: =K77+K78 -> 26343.317 | L85: =L77+L78 -> 30613.576
A87: # | B87: SUPPORTING SCHEDULES - LEASES, DEPRECIATION AND TREASURY
B88: Lease rent paid (Ind AS 116) | D88: =RevBuild!D10*Assumptions!D38+Assumptions!D39 -> 569.8535 | E88: =RevBuild!E10*Assumptions!E38+Assumptions!E39 -> 1014.4295 | F88: =RevBuild!F10*Assumptions!F38+Assumptions!F39 -> 1530.6 | G88: =RevBuild!G10*Assumptions!G38+Assumptions!G39 -> 2095.8 | H88: =RevBuild!H10*Assumptions!H38+Assumptions!H39 -> 2679 | I88: =RevBuild!I10*Assumptions!I38+Assumptions!I39 -> 3253.2 | J88: =RevBuild!J10*Assumptions!J38+Assumptions!J39 -> 3809.3 | K88: =RevBuild!K10*Assumptions!K38+Assumptions!K39 -> 4354 | L88: =RevBuild!L10*Assumptions!L38+Assumptions!L39 -> 4870.2
B89: Lease interest expense | D89: 154 | E89: =(E50+D50)/2*Assumptions!E42 -> 370.425 | F89: =(F50+E50)/2*Assumptions!F42 -> 637.34 | G89: =(G50+F50)/2*Assumptions!G42 -> 863.995 | H89: =(H50+G50)/2*Assumptions!H42 -> 1064.58 | I89: =(I50+H50)/2*Assumptions!I42 -> 1245.42 | J89: =(J50+I50)/2*Assumptions!J42 -> 1406.515 | K89: =(K50+J50)/2*Assumptions!K42 -> 1547.92 | L89: =(L50+K50)/2*Assumptions!L42 -> 1669.69
B90: Lease principal repayment | D90: =D88-D89 -> 415.8535 | E90: =E88-E89 -> 644.0045 | F90: =F88-F89 -> 893.26 | G90: =G88-G89 -> 1231.805 | H90: =H88-H89 -> 1614.42 | I90: =I88-I89 -> 2007.78 | J90: =J88-J89 -> 2402.785 | K90: =K88-K89 -> 2806.08 | L90: =L88-L89 -> 3200.51
B91: New lease additions (balancing) | E91: =E50-D50+E90 -> 3289.0045 | F91: =F50-E50+F90 -> 3101.26 | G91: =G50-F50+G90 -> 3144.805 | H91: =H50-G50+H90 -> 3348.42 | I91: =I50-H50+I90 -> 3561.78 | J91: =J50-I50+J90 -> 3777.785 | K91: =K50-J50+K90 -> 4002.08 | L91: =L50-K50+L90 -> 4218.51
B92: Right-of-use depreciation | D92: 420 | E92: =D41+E91-E41 -> 1040.5045 | F92: =E41+F91-F41 -> 1224.46 | G92: =F41+G91-G41 -> 1518.755 | H92: =G41+H91-H41 -> 1874.52 | I92: =H41+I91-I41 -> 2240.88 | J92: =I41+J91-J41 -> 2609.035 | K92: =J41+K91-K41 -> 2985.48 | L92: =K41+L91-L41 -> 3353.21
B93: PP&E depreciation | D93: 193 | E93: =(D40+0.5*-E78)*Assumptions!E46 -> 284.71602 | F93: =(E40+0.5*-F78)*Assumptions!F46 -> 460.46701 | G93: =(F40+0.5*-G78)*Assumptions!G46 -> 649.9137 | H93: =(G40+0.5*-H78)*Assumptions!H46 -> 847.44574 | I93: =(H40+0.5*-I78)*Assumptions!I46 -> 1047.2581 | J93: =(I40+0.5*-J78)*Assumptions!J46 -> 1246.7182 | K93: =(J40+0.5*-K78)*Assumptions!K46 -> 1441.9658 | L93: =(K40+0.5*-L78)*Assumptions!L46 -> 1630.6289
B94: Net cash / (debt) after lease liabilities | D94: =D36-D50 -> 16812 | E94: =E36-E50 -> 18911.497 | F94: =F36-F50 -> 21407.004 | G94: =G36-G50 -> 27159.137 | H94: =H36-H50 -> 37380.317 | I94: =I36-I50 -> 51942.797 | J94: =J36-J50 -> 70080.493 | K94: =K36-K50 -> 92421.73 | L94: =L36-L50 -> 118816.8
B95: Memo: net cash before lease liabilities | D95: =D36 -> 18857 | E95: =E36 -> 23601.497 | F95: =F36 -> 28305.004 | G95: =G36 -> 35970.137 | H95: =H36 -> 47925.317 | I95: =I36 -> 64041.797 | J95: =J36 -> 83554.493 | K95: =K36 -> 107091.73 | L95: =L36 -> 134504.8
B96: Interest-earning cash, average (non-circular basis) | E96: =D36+0.5*(E20*(1-Assumptions!E56)+E78+E80) -> 18194.649 | F96: =E36+0.5*(F20*(1-Assumptions!F56)+F78+F80) -> 23755.101 | G96: =F36+0.5*(G20*(1-Assumptions!G56)+G78+G80) -> 29708.33 | H96: =G36+0.5*(H20*(1-Assumptions!H56)+H78+H80) -> 38974.78 | I96: =H36+0.5*(I20*(1-Assumptions!I56)+I78+I80) -> 52409.684 | J96: =I36+0.5*(J20*(1-Assumptions!J56)+J78+J80) -> 69590.911 | K96: =J36+0.5*(K20*(1-Assumptions!K56)+K78+K80) -> 90386.41 | L96: =K36+0.5*(L20*(1-Assumptions!L56)+L78+L80) -> 115053.06
B97: The lease schedule is derived, not assumed, and reproduces disclosure: ₹2.20cr of lease liability per closing dark store plus the office and warehouse block gives ₹3,565cr at 31-Mar-2025, which at an 8.5% discount rate produces the ₹154cr of FY25 finance costs the company actually reported, and the FY26E schedule produces roughly ₹106cr a quarter against the ₹106cr reported in Q3FY26. Right-of-use assets are set at 90% of the lease liability, the usual steady-state relationship when an asset depreciates straight-line against a liability that unwinds on an effective-interest basis; right-of-use depreciation then falls out of the roll-forward rather than being assumed. Treasury income is measured off opening cash adjusted for half of the year's known capital outflows, deliberately excluding in-year operating generation, in order to avoid a circular reference. That understates finance income and is therefore conservative. Eternal carries no borrowings; all finance cost is lease interest.

Sheet Ratios
B2: Ratio Analysis & DuPont Decomposition
B3: One year of audited history and eight forecast years. All ratios computed live from the Model tab.
A5: # | B5: Ratio | C5: Units | D5: FY25A | E5: FY26E | F5: FY27E | G5: FY28E | H5: FY29E | I5: FY30E | J5: FY31E | K5: FY32E | L5: FY33E
A6: # | B6: PROFITABILITY
B7: Gross margin | D7: =Model!D10/Model!D7 -> 0.73063172 | E7: =Model!E10/Model!E7 -> 0.42398026 | F7: =Model!F10/Model!F7 -> 0.32729237 | G7: =Model!G10/Model!G7 -> 0.31336164 | H7: =Model!H10/Model!H7 -> 0.3049247 | I7: =Model!I10/Model!I7 -> 0.29977184 | J7: =Model!J10/Model!J7 -> 0.29542783 | K7: =Model!K10/Model!K7 -> 0.292633 | L7: =Model!L10/Model!L7 -> 0.29099637
B8: Adjusted EBITDA margin on B2C net order value | D8: =Model!D20/RevBuild!D43 -> 0.012296312 | E8: =Model!E20/RevBuild!E43 -> 0.011910256 | F8: =Model!F20/RevBuild!F43 -> 0.028585351 | G8: =Model!G20/RevBuild!G43 -> 0.04058657 | H8: =Model!H20/RevBuild!H43 -> 0.049657539 | I8: =Model!I20/RevBuild!I43 -> 0.056975675 | J8: =Model!J20/RevBuild!J43 -> 0.06067865 | K8: =Model!K20/RevBuild!K43 -> 0.063363909 | L8: =Model!L20/RevBuild!L43 -> 0.064937872
B9: EBITDA margin on revenue | D9: =Model!D23/Model!D7 -> 0.031509307 | E9: =Model!E23/Model!E7 -> 0.024820382 | F9: =Model!F23/Model!F7 -> 0.04869002 | G9: =Model!G23/Model!G7 -> 0.065580636 | H9: =Model!H23/Model!H7 -> 0.077337553 | I9: =Model!I23/Model!I7 -> 0.086453803 | J9: =Model!J23/Model!J7 -> 0.090892894 | K9: =Model!K23/Model!K7 -> 0.094246578 | L9: =Model!L23/Model!L7 -> 0.096246166
B10: EBIT margin on revenue | D10: =Model!D26/Model!D7 -> -0.011125389 | E10: =Model!E26/Model!E7 -> -0.0041756901 | F10: =Model!F26/Model!F7 -> 0.028663229 | G10: =Model!G26/Model!G7 -> 0.048010761 | H10: =Model!H26/Model!H7 -> 0.060997828 | I10: =Model!I26/Model!I7 -> 0.070856497 | J10: =Model!J26/Model!J7 -> 0.075689526 | K10: =Model!K26/Model!K7 -> 0.079194361 | L10: =Model!L26/Model!L7 -> 0.08121118
B11: Net margin | D11: =Model!D31/Model!D7 -> 0.026061952 | E11: =Model!E31/Model!E7 -> 0.0070046221 | F11: =Model!F31/Model!F7 -> 0.026784075 | G11: =Model!G31/Model!G7 -> 0.04334092 | H11: =Model!H31/Model!H7 -> 0.056292123 | I11: =Model!I31/Model!I7 -> 0.063805551 | J11: =Model!J31/Model!J7 -> 0.06646667 | K11: =Model!K31/Model!K7 -> 0.071020989 | L11: =Model!L31/Model!L7 -> 0.074760756
B12: Return on equity | E12: =Model!E31/((Model!E54+Model!D54)/2) -> 0.012387608 | F12: =Model!F31/((Model!F54+Model!E54)/2) -> 0.077092437 | G12: =Model!G31/((Model!G54+Model!F54)/2) -> 0.15252823 | H12: =Model!H31/((Model!H54+Model!G54)/2) -> 0.21198054 | I12: =Model!I31/((Model!I54+Model!H54)/2) -> 0.23461568 | J12: =Model!J31/((Model!J54+Model!I54)/2) -> 0.22749789 | K12: =Model!K31/((Model!K54+Model!J54)/2) -> 0.22100375 | L12: =Model!L31/((Model!L54+Model!K54)/2) -> 0.20851982
B13: Return on capital employed (EBIT basis) | E13: =Model!E26/((Model!E54+Model!E50+Model!D54+Model!D50)/2) -> -0.0066592552 | F13: =Model!F26/((Model!F54+Model!F50+Model!E54+Model!E50)/2) -> 0.070249022 | G13: =Model!G26/((Model!G54+Model!G50+Model!F54+Model!F50)/2) -> 0.1402135 | H13: =Model!H26/((Model!H54+Model!H50+Model!G54+Model!G50)/2) -> 0.19059086 | I13: =Model!I26/((Model!I54+Model!I50+Model!H54+Model!H50)/2) -> 0.21930375 | J13: =Model!J26/((Model!J54+Model!J50+Model!I54+Model!I50)/2) -> 0.22220252 | K13: =Model!K26/((Model!K54+Model!K50+Model!J54+Model!J50)/2) -> 0.21541862 | L13: =Model!L26/((Model!L54+Model!L50+Model!K54+Model!K50)/2) -> 0.20152458
B14: Return on invested capital (NOPAT / IC) | D14: =Model!D26*(1-Assumptions!D56)/(Model!D54+Model!D50-Model!D36) -> -0.01260637 | E14: =Model!E26*(1-Assumptions!E56)/(Model!E54+Model!E50-Model!E36) -> -0.0090600744 | F14: =Model!F26*(1-Assumptions!F56)/(Model!F54+Model!F50-Model!F36) -> 0.13780664 | G14: =Model!G26*(1-Assumptions!G56)/(Model!G54+Model!G50-Model!G36) -> 0.33867015 | H14: =Model!H26*(1-Assumptions!H56)/(Model!H54+Model!H50-Model!H36) -> 0.56788751 | I14: =Model!I26*(1-Assumptions!I56)/(Model!I54+Model!I50-Model!I36) -> 0.77272357 | J14: =Model!J26*(1-Assumptions!J56)/(Model!J54+Model!J50-Model!J36) -> 0.9171398 | K14: =Model!K26*(1-Assumptions!K56)/(Model!K54+Model!K50-Model!K36) -> 1.0818506 | L14: =Model!L26*(1-Assumptions!L56)/(Model!L54+Model!L50-Model!L36) -> 1.2241665
B15: Memo: goodwill as % of invested capital | D15: =Model!D42/(Model!D54+Model!D50-Model!D36) -> 0.42947057 | E15: =Model!E42/(Model!E54+Model!E50-Model!E36) -> 0.46037419 | F15: =Model!F42/(Model!F54+Model!F50-Model!F36) -> 0.42886762 | G15: =Model!G42/(Model!G54+Model!G50-Model!G36) -> 0.39931634 | H15: =Model!H42/(Model!H54+Model!H50-Model!H36) -> 0.38004797 | I15: =Model!I42/(Model!I54+Model!I50-Model!I36) -> 0.36628026 | J15: =Model!J42/(Model!J54+Model!J50-Model!J36) -> 0.35601301 | K15: =Model!K42/(Model!K54+Model!K50-Model!K36) -> 0.34817898 | L15: =Model!L42/(Model!L54+Model!L50-Model!L36) -> 0.34216667
A16: # | B16: DUPONT DECOMPOSITION (3-step)
B17: Net margin (PAT / revenue) | E17: =Model!E31/Model!E7 -> 0.0070046221 | F17: =Model!F31/Model!F7 -> 0.026784075 | G17: =Model!G31/Model!G7 -> 0.04334092 | H17: =Model!H31/Model!H7 -> 0.056292123 | I17: =Model!I31/Model!I7 -> 0.063805551 | J17: =Model!J31/Model!J7 -> 0.06646667 | K17: =Model!K31/Model!K7 -> 0.071020989 | L17: =Model!L31/Model!L7 -> 0.074760756
B18: × Asset turnover (revenue / average assets) | E18: =Model!E7/((Model!E45+Model!D45)/2) -> 1.3904236 | F18: =Model!F7/((Model!F45+Model!E45)/2) -> 1.9669629 | G18: =Model!G7/((Model!G45+Model!F45)/2) -> 2.2073651 | H18: =Model!H7/((Model!H45+Model!G45)/2) -> 2.3049415 | I18: =Model!I7/((Model!I45+Model!H45)/2) -> 2.2744204 | J18: =Model!J7/((Model!J45+Model!I45)/2) -> 2.1756765 | K18: =Model!K7/((Model!K45+Model!J45)/2) -> 2.0471018 | L18: =Model!L7/((Model!L45+Model!K45)/2) -> 1.9034809
B19: × Equity multiplier (average assets / average equity) | E19: =((Model!E45+Model!D45)/2)/((Model!E54+Model!D54)/2) -> 1.2719077 | F19: =((Model!F45+Model!E45)/2)/((Model!F54+Model!E54)/2) -> 1.4633188 | G19: =((Model!G45+Model!F45)/2)/((Model!G54+Model!F54)/2) -> 1.5943289 | H19: =((Model!H45+Model!G45)/2)/((Model!H54+Model!G54)/2) -> 1.6337607 | I19: =((Model!I45+Model!H45)/2)/((Model!I54+Model!H54)/2) -> 1.616694 | J19: =((Model!J45+Model!I45)/2)/((Model!J54+Model!I54)/2) -> 1.5731826 | K19: =((Model!K45+Model!J45)/2)/((Model!K54+Model!J54)/2) -> 1.5201046 | L19: =((Model!L45+Model!K45)/2)/((Model!L54+Model!K54)/2) -> 1.4652952
B20: = Return on equity | E20: =E17*E18*E19 -> 0.012387608 | F20: =F17*F18*F19 -> 0.077092437 | G20: =G17*G18*G19 -> 0.15252823 | H20: =H17*H18*H19 -> 0.21198054 | I20: =I17*I18*I19 -> 0.23461568 | J20: =J17*J18*J19 -> 0.22749789 | K20: =K17*K18*K19 -> 0.22100375 | L20: =L17*L18*L19 -> 0.20851982
B21: Cross-check vs direct ROE (must be zero) | E21: =E20-E12 -> 0 | F21: =F20-F12 -> 0 | G21: =G20-G12 -> 0 | H21: =H20-H12 -> 0 | I21: =I20-I12 -> 0 | J21: =J20-J12 -> 0 | K21: =K20-K12 -> 0 | L21: =L20-L12 -> 0
A23: # | B23: LIQUIDITY & LEVERAGE
B24: Net cash / (debt) after leases (₹ cr) | D24: =Model!D94 -> 16812 | E24: =Model!E94 -> 18911.497 | F24: =Model!F94 -> 21407.004 | G24: =Model!G94 -> 27159.137 | H24: =Model!H94 -> 37380.317 | I24: =Model!I94 -> 51942.797 | J24: =Model!J94 -> 70080.493 | K24: =Model!K94 -> 92421.73 | L24: =Model!L94 -> 118816.8
B25: Net cash as % of market capitalisation | D25: =Model!D94/Assumptions!$D$8 -> 0.071729895 | E25: =Model!E94/Assumptions!$D$8 -> 0.080687584 | F25: =Model!F94/Assumptions!$D$8 -> 0.091334888 | G25: =Model!G94/Assumptions!$D$8 -> 0.11587688 | H25: =Model!H94/Assumptions!$D$8 -> 0.15948645 | I25: =Model!I94/Assumptions!$D$8 -> 0.22161857 | J25: =Model!J94/Assumptions!$D$8 -> 0.29900466 | K25: =Model!K94/Assumptions!$D$8 -> 0.39432554 | L25: =Model!L94/Assumptions!$D$8 -> 0.50694244
B26: Lease liabilities / equity | D26: =Model!D50/Model!D54 -> 0.067453904 | E26: =Model!E50/Model!E54 -> 0.1488419 | F26: =Model!F50/Model!F54 -> 0.19747507 | G26: =Model!G50/Model!G54 -> 0.21137626 | H26: =Model!H50/Model!H54 -> 0.20031705 | I26: =Model!I50/Model!I54 -> 0.17851013 | J26: =Model!J50/Model!J54 -> 0.15599957 | K26: =Model!K50/Model!K54 -> 0.13448866 | L26: =Model!L50/Model!L54 -> 0.1155504
B27: Net debt / adjusted EBITDA | D27: =-Model!D94/Model!D20 -> -21.949231 | E27: =-Model!E94/Model!E20 -> -16.409033 | F27: =-Model!F94/Model!F20 -> -5.3718212 | G27: =-Model!G94/Model!G20 -> -3.5477092 | H27: =-Model!H94/Model!H20 -> -3.1108025 | I27: =-Model!I94/Model!I20 -> -3.074068 | J27: =-Model!J94/Model!J20 -> -3.3011878 | K27: =-Model!K94/Model!K20 -> -3.6362455 | L27: =-Model!L94/Model!L20 -> -4.0754931
B28: Interest coverage (EBIT / lease interest) | D28: =-Model!D26/Model!D29 -> -1.4623189 | E28: =-Model!E26/Model!E29 -> -0.6162806 | F28: =-Model!F26/Model!F29 -> 4.3002608 | G28: =-Model!G26/Model!G29 -> 7.4914004 | H28: =-Model!H26/Model!H29 -> 10.176152 | I28: =-Model!I26/Model!I29 -> 12.595871 | J28: =-Model!J26/Model!J29 -> 14.196378 | K28: =-Model!K26/Model!K29 -> 15.558527 | L28: =-Model!L26/Model!L29 -> 16.60807
A30: # | B30: EFFICIENCY
B31: Inventory days (on COGS) | D31: =Model!D37/-Model!D9*365 -> 44.51644 | E31: =Model!E37/-Model!E9*365 -> 14 | F31: =Model!F37/-Model!F9*365 -> 14 | G31: =Model!G37/-Model!G9*365 -> 14 | H31: =Model!H37/-Model!H9*365 -> 14 | I31: =Model!I37/-Model!I9*365 -> 14 | J31: =Model!J37/-Model!J9*365 -> 14 | K31: =Model!K37/-Model!K9*365 -> 14 | L31: =Model!L37/-Model!L9*365 -> 14
B32: Trade payable days (on COGS) | D32: =Model!D48/-Model!D9*365 -> 104.69731 | E32: =Model!E48/-Model!E9*365 -> 30 | F32: =Model!F48/-Model!F9*365 -> 30 | G32: =Model!G48/-Model!G9*365 -> 30 | H32: =Model!H48/-Model!H9*365 -> 30 | I32: =Model!I48/-Model!I9*365 -> 30 | J32: =Model!J48/-Model!J9*365 -> 30 | K32: =Model!K48/-Model!K9*365 -> 30 | L32: =Model!L48/-Model!L9*365 -> 30
B33: Trade receivable days (on revenue) | D33: =Model!D38/Model!D7*365 -> 35.00022 | E33: =Model!E38/Model!E7*365 -> 8 | F33: =Model!F38/Model!F7*365 -> 8 | G33: =Model!G38/Model!G7*365 -> 8 | H33: =Model!H38/Model!H7*365 -> 8 | I33: =Model!I38/Model!I7*365 -> 8 | J33: =Model!J38/Model!J7*365 -> 8 | K33: =Model!K38/Model!K7*365 -> 8 | L33: =Model!L38/Model!L7*365 -> 8
B34: Cash conversion cycle (days) | D34: =Model!D37/-Model!D9*365+Model!D38/Model!D7*365-Model!D48/-Model!D9*365 -> -25.180651 | E34: =Model!E37/-Model!E9*365+Model!E38/Model!E7*365-Model!E48/-Model!E9*365 -> -8 | F34: =Model!F37/-Model!F9*365+Model!F38/Model!F7*365-Model!F48/-Model!F9*365 -> -8 | G34: =Model!G37/-Model!G9*365+Model!G38/Model!G7*365-Model!G48/-Model!G9*365 -> -8 | H34: =Model!H37/-Model!H9*365+Model!H38/Model!H7*365-Model!H48/-Model!H9*365 -> -8 | I34: =Model!I37/-Model!I9*365+Model!I38/Model!I7*365-Model!I48/-Model!I9*365 -> -8 | J34: =Model!J37/-Model!J9*365+Model!J38/Model!J7*365-Model!J48/-Model!J9*365 -> -8 | K34: =Model!K37/-Model!K9*365+Model!K38/Model!K7*365-Model!K48/-Model!K9*365 -> -8 | L34: =Model!L37/-Model!L9*365+Model!L38/Model!L7*365-Model!L48/-Model!L9*365 -> -8
B35: Capex as % of B2C net order value | E35: =-Model!E78/RevBuild!E43 -> 0.012989614 | F35: =-Model!F78/RevBuild!F43 -> 0.010826913 | G35: =-Model!G78/RevBuild!G43 -> 0.0094351465 | H35: =-Model!H78/RevBuild!H43 -> 0.0082209372 | I35: =-Model!I78/RevBuild!I43 -> 0.0074290744 | J35: =-Model!J78/RevBuild!J43 -> 0.0068157848 | K35: =-Model!K78/RevBuild!K43 -> 0.0063558315 | L35: =-Model!L78/RevBuild!L43 -> 0.0059978451
B36: NOV per average dark store per day (₹ lakh) | D36: =RevBuild!D11 -> 6.71 | E36: =RevBuild!E11 -> 7.39 | F36: =RevBuild!F11 -> 7.9 | G36: =RevBuild!G11 -> 8.5 | H36: =RevBuild!H11 -> 9.15 | I36: =RevBuild!I11 -> 9.8 | J36: =RevBuild!J11 -> 10.4 | K36: =RevBuild!K11 -> 10.95 | L36: =RevBuild!L11 -> 11.45
A38: # | B38: VALUATION AT REFERENCE PRICE
B39: P / E | D39: =Assumptions!$D$6/Model!D33 -> 404.35443 | E39: =Assumptions!$D$6/Model!E33 -> 612.04585 | F39: =Assumptions!$D$6/Model!F33 -> 91.516979 | G39: =Assumptions!$D$6/Model!G33 -> 40.113025 | H39: =Assumptions!$D$6/Model!H33 -> 23.443585 | I39: =Assumptions!$D$6/Model!I33 -> 16.591909 | J39: =Assumptions!$D$6/Model!J33 -> 13.366852 | K39: =Assumptions!$D$6/Model!K33 -> 10.851999 | L39: =Assumptions!$D$6/Model!L33 -> 9.1813448
B40: EV / adjusted EBITDA | D40: =(Assumptions!$D$8-Model!D94)/Model!D20 -> 284.04914 | E40: =(Assumptions!$D$8-Model!E94)/Model!E20 -> 186.95599 | F40: =(Assumptions!$D$8-Model!F94)/Model!F20 -> 53.442738 | G40: =(Assumptions!$D$8-Model!G94)/Model!G20 -> 27.068487 | H40: =(Assumptions!$D$8-Model!H94)/Model!H20 -> 16.394318 | I40: =(Assumptions!$D$8-Model!I94)/Model!I20 -> 10.796918 | J40: =(Assumptions!$D$8-Model!J94)/Model!J20 -> 7.7394019 | K40: =(Assumptions!$D$8-Model!K94)/Model!K20 -> 5.5851849 | L40: =(Assumptions!$D$8-Model!L94)/Model!L20 -> 3.9638676
B41: EV / revenue | D41: =(Assumptions!$D$8-Model!D94)/Model!D7 -> 10.748452 | E41: =(Assumptions!$D$8-Model!E94)/Model!E7 -> 3.9412301 | F41: =(Assumptions!$D$8-Model!F94)/Model!F7 -> 2.2273178 | G41: =(Assumptions!$D$8-Model!G94)/Model!G7 -> 1.5370794 | H41: =(Assumptions!$D$8-Model!H94)/Model!H7 -> 1.1092166 | I41: =(Assumptions!$D$8-Model!I94)/Model!I7 -> 0.8240381 | J41: =(Assumptions!$D$8-Model!J94)/Model!J7 -> 0.62279939 | K41: =(Assumptions!$D$8-Model!K94)/Model!K7 -> 0.46680523 | L41: =(Assumptions!$D$8-Model!L94)/Model!L7 -> 0.33843682
B42: EV / B2C net order value | D42: =(Assumptions!$D$8-Model!D94)/RevBuild!D43 -> 3.4927568 | E42: =(Assumptions!$D$8-Model!E94)/RevBuild!E43 -> 2.2266937 | F42: =(Assumptions!$D$8-Model!F94)/RevBuild!F43 -> 1.5276794 | G42: =(Assumptions!$D$8-Model!G94)/RevBuild!G43 -> 1.0986171 | H42: =(Assumptions!$D$8-Model!H94)/RevBuild!H43 -> 0.81410149 | I42: =(Assumptions!$D$8-Model!I94)/RevBuild!I43 -> 0.61516168 | J42: =(Assumptions!$D$8-Model!J94)/RevBuild!J43 -> 0.46961646 | K42: =(Assumptions!$D$8-Model!K94)/RevBuild!K43 -> 0.35389914 | L42: =(Assumptions!$D$8-Model!L94)/RevBuild!L43 -> 0.25740512
B43: P / B | D43: =Assumptions!$D$8/Model!D54 -> 7.7309518 | E43: =Assumptions!$D$8/Model!E54 -> 7.4382635 | F43: =Assumptions!$D$8/Model!F54 -> 6.7097801 | G43: =Assumptions!$D$8/Model!G54 -> 5.6227684 | H43: =Assumptions!$D$8/Model!H54 -> 4.4523626 | I43: =Assumptions!$D$8/Model!I54 -> 3.4580604 | J43: =Assumptions!$D$8/Model!J54 -> 2.7136014 | K43: =Assumptions!$D$8/Model!K54 -> 2.1486948 | L43: =Assumptions!$D$8/Model!L54 -> 1.7263269
B44: Free cash flow yield | E44: =Model!E85/Assumptions!$D$8 -> 0.02299052 | F44: =Model!F85/Assumptions!$D$8 -> 0.023879106 | G44: =Model!G85/Assumptions!$D$8 -> 0.037959579 | H44: =Model!H85/Assumptions!$D$8 -> 0.057895907 | I44: =Model!I85/Assumptions!$D$8 -> 0.077328769 | J44: =Model!J85/Assumptions!$D$8 -> 0.093504349 | K44: =Model!K85/Assumptions!$D$8 -> 0.11239611 | L44: =Model!L85/Assumptions!$D$8 -> 0.13061555

Sheet WACC
B2: Cost of Capital - CAPM Build
B3: Built up from observable inputs. Peer betas are unlevered at each peer's own capital structure and relevered at Eternal's.
A5: # | B5: Peer | C5: Levered beta | D5: Debt / equity | E5: Tax rate | F5: Unlevered beta
B6: Swiggy Limited | C6: 1.35 | D6: 0.05 | E6: 0.25 | F6: =C6/(1+(1-E6)*D6) -> 1.3012048
B7: Avenue Supermarts (DMart) | C7: 0.72 | D7: 0.06 | E7: 0.255 | F7: =C7/(1+(1-E7)*D7) -> 0.68919307
B8: FSN E-Commerce Ventures (Nykaa) | C8: 1.05 | D8: 0.1 | E8: 0.25 | F8: =C8/(1+(1-E8)*D8) -> 0.97674419
B9: Info Edge (India) | C9: 0.95 | D9: 0.01 | E9: 0.25 | F9: =C9/(1+(1-E9)*D9) -> 0.94292804
B10: Brainbees Solutions (FirstCry) | C10: 1.15 | D10: 0.05 | E10: 0.25 | F10: =C10/(1+(1-E10)*D10) -> 1.1084337
B11: Median unlevered beta | F11: =MEDIAN(F6:F10) -> 0.97674419
A13: # | B13: COST OF EQUITY
B14: Risk-free rate - India 10Y G-Sec | D14: 0.068
B15: Equity risk premium - India | D15: 0.06
B16: Target debt / equity (market values, leases only) | D16: =D25/D24 -> 0.020010303
B17: Marginal tax rate | D17: 0.25
B18: Relevered beta for Eternal | D18: =F11*(1+(1-D17)*D16) -> 0.9914029
B19: Cost of equity = Rf + β × ERP | D19: =D14+D18*D15 -> 0.12748417
A21: # | B21: COST OF DEBT & CAPITAL WEIGHTS
B22: Pre-tax cost of debt (lease discount rate) | D22: =Assumptions!$E$42 -> 0.11
B23: After-tax cost of debt | D23: =D22*(1-D17) -> 0.0825
B24: Market capitalisation (₹ cr) | D24: =Assumptions!$D$8 -> 234379.26
B25: Lease liabilities, FY26E (₹ cr) | D25: =Model!E50 -> 4690
B26: Weight of equity | D26: =D24/(D24+D25) -> 0.98038225
B27: Weight of debt | D27: =D25/(D24+D25) -> 0.019617746
B29: WACC | D29: =D26*D19+D27*D23 -> 0.12660169

Sheet Sensitivity
A1: ADITYA NAIR RESEARCH
A2: Sensitivity - Value per Share
A3: WACC × terminal growth. Live formulas throughout; no Excel data table, so the grid cannot silently fail to recalculate.
A5: VALUE PER SHARE (₹) - WACC (rows) × TERMINAL GROWTH (columns)
A6: WACC \ g | B6: 0.055 | C6: 0.06 | D6: 0.065 | E6: 0.07 | F6: 0.075
A7: =Assumptions!$D$59+-0.01 -> 0.11660169 | B7: =(DCF!$F$14/(1+$A7)^1+DCF!$G$14/(1+$A7)^2+DCF!$H$14/(1+$A7)^3+DCF!$I$14/(1+$A7)^4+DCF!$J$14/(1+$A7)^5+DCF!$K$14/(1+$A7)^6+DCF!$L$14/(1+$A7)^7+DCF!$L$14*(1+B$6)/($A7-B$6)/(1+$A7)^7+DCF!$L$34)/DCF!$L$38 -> 249.30321 | C7: =(DCF!$F$14/(1+$A7)^1+DCF!$G$14/(1+$A7)^2+DCF!$H$14/(1+$A7)^3+DCF!$I$14/(1+$A7)^4+DCF!$J$14/(1+$A7)^5+DCF!$K$14/(1+$A7)^6+DCF!$L$14/(1+$A7)^7+DCF!$L$14*(1+C$6)/($A7-C$6)/(1+$A7)^7+DCF!$L$34)/DCF!$L$38 -> 265.76831 | D7: =(DCF!$F$14/(1+$A7)^1+DCF!$G$14/(1+$A7)^2+DCF!$H$14/(1+$A7)^3+DCF!$I$14/(1+$A7)^4+DCF!$J$14/(1+$A7)^5+DCF!$K$14/(1+$A7)^6+DCF!$L$14/(1+$A7)^7+DCF!$L$14*(1+D$6)/($A7-D$6)/(1+$A7)^7+DCF!$L$34)/DCF!$L$38 -> 285.42422 | E7: =(DCF!$F$14/(1+$A7)^1+DCF!$G$14/(1+$A7)^2+DCF!$H$14/(1+$A7)^3+DCF!$I$14/(1+$A7)^4+DCF!$J$14/(1+$A7)^5+DCF!$K$14/(1+$A7)^6+DCF!$L$14/(1+$A7)^7+DCF!$L$14*(1+E$6)/($A7-E$6)/(1+$A7)^7+DCF!$L$34)/DCF!$L$38 -> 309.29798 | F7: =(DCF!$F$14/(1+$A7)^1+DCF!$G$14/(1+$A7)^2+DCF!$H$14/(1+$A7)^3+DCF!$I$14/(1+$A7)^4+DCF!$J$14/(1+$A7)^5+DCF!$K$14/(1+$A7)^6+DCF!$L$14/(1+$A7)^7+DCF!$L$14*(1+F$6)/($A7-F$6)/(1+$A7)^7+DCF!$L$34)/DCF!$L$38 -> 338.9104
A8: =Assumptions!$D$59+-0.005 -> 0.12160169 | B8: =(DCF!$F$14/(1+$A8)^1+DCF!$G$14/(1+$A8)^2+DCF!$H$14/(1+$A8)^3+DCF!$I$14/(1+$A8)^4+DCF!$J$14/(1+$A8)^5+DCF!$K$14/(1+$A8)^6+DCF!$L$14/(1+$A8)^7+DCF!$L$14*(1+B$6)/($A8-B$6)/(1+$A8)^7+DCF!$L$34)/DCF!$L$38 -> 229.96646 | C8: =(DCF!$F$14/(1+$A8)^1+DCF!$G$14/(1+$A8)^2+DCF!$H$14/(1+$A8)^3+DCF!$I$14/(1+$A8)^4+DCF!$J$14/(1+$A8)^5+DCF!$K$14/(1+$A8)^6+DCF!$L$14/(1+$A8)^7+DCF!$L$14*(1+C$6)/($A8-C$6)/(1+$A8)^7+DCF!$L$34)/DCF!$L$38 -> 243.58926 | D8: =(DCF!$F$14/(1+$A8)^1+DCF!$G$14/(1+$A8)^2+DCF!$H$14/(1+$A8)^3+DCF!$I$14/(1+$A8)^4+DCF!$J$14/(1+$A8)^5+DCF!$K$14/(1+$A8)^6+DCF!$L$14/(1+$A8)^7+DCF!$L$14*(1+D$6)/($A8-D$6)/(1+$A8)^7+DCF!$L$34)/DCF!$L$38 -> 259.61884 | E8: =(DCF!$F$14/(1+$A8)^1+DCF!$G$14/(1+$A8)^2+DCF!$H$14/(1+$A8)^3+DCF!$I$14/(1+$A8)^4+DCF!$J$14/(1+$A8)^5+DCF!$K$14/(1+$A8)^6+DCF!$L$14/(1+$A8)^7+DCF!$L$14*(1+E$6)/($A8-E$6)/(1+$A8)^7+DCF!$L$34)/DCF!$L$38 -> 278.75483 | F8: =(DCF!$F$14/(1+$A8)^1+DCF!$G$14/(1+$A8)^2+DCF!$H$14/(1+$A8)^3+DCF!$I$14/(1+$A8)^4+DCF!$J$14/(1+$A8)^5+DCF!$K$14/(1+$A8)^6+DCF!$L$14/(1+$A8)^7+DCF!$L$14*(1+F$6)/($A8-F$6)/(1+$A8)^7+DCF!$L$34)/DCF!$L$38 -> 301.99711
A9: =Assumptions!$D$59+0 -> 0.12660169 | B9: =(DCF!$F$14/(1+$A9)^1+DCF!$G$14/(1+$A9)^2+DCF!$H$14/(1+$A9)^3+DCF!$I$14/(1+$A9)^4+DCF!$J$14/(1+$A9)^5+DCF!$K$14/(1+$A9)^6+DCF!$L$14/(1+$A9)^7+DCF!$L$14*(1+B$6)/($A9-B$6)/(1+$A9)^7+DCF!$L$34)/DCF!$L$38 -> 213.37071 | C9: =(DCF!$F$14/(1+$A9)^1+DCF!$G$14/(1+$A9)^2+DCF!$H$14/(1+$A9)^3+DCF!$I$14/(1+$A9)^4+DCF!$J$14/(1+$A9)^5+DCF!$K$14/(1+$A9)^6+DCF!$L$14/(1+$A9)^7+DCF!$L$14*(1+C$6)/($A9-C$6)/(1+$A9)^7+DCF!$L$34)/DCF!$L$38 -> 224.78228 | D9: =(DCF!$F$14/(1+$A9)^1+DCF!$G$14/(1+$A9)^2+DCF!$H$14/(1+$A9)^3+DCF!$I$14/(1+$A9)^4+DCF!$J$14/(1+$A9)^5+DCF!$K$14/(1+$A9)^6+DCF!$L$14/(1+$A9)^7+DCF!$L$14*(1+D$6)/($A9-D$6)/(1+$A9)^7+DCF!$L$34)/DCF!$L$38 -> 238.04632 | E9: =(DCF!$F$14/(1+$A9)^1+DCF!$G$14/(1+$A9)^2+DCF!$H$14/(1+$A9)^3+DCF!$I$14/(1+$A9)^4+DCF!$J$14/(1+$A9)^5+DCF!$K$14/(1+$A9)^6+DCF!$L$14/(1+$A9)^7+DCF!$L$14*(1+E$6)/($A9-E$6)/(1+$A9)^7+DCF!$L$34)/DCF!$L$38 -> 253.65376 | F9: =(DCF!$F$14/(1+$A9)^1+DCF!$G$14/(1+$A9)^2+DCF!$H$14/(1+$A9)^3+DCF!$I$14/(1+$A9)^4+DCF!$J$14/(1+$A9)^5+DCF!$K$14/(1+$A9)^6+DCF!$L$14/(1+$A9)^7+DCF!$L$14*(1+F$6)/($A9-F$6)/(1+$A9)^7+DCF!$L$34)/DCF!$L$38 -> 272.2858
A10: =Assumptions!$D$59+0.005 -> 0.13160169 | B10: =(DCF!$F$14/(1+$A10)^1+DCF!$G$14/(1+$A10)^2+DCF!$H$14/(1+$A10)^3+DCF!$I$14/(1+$A10)^4+DCF!$J$14/(1+$A10)^5+DCF!$K$14/(1+$A10)^6+DCF!$L$14/(1+$A10)^7+DCF!$L$14*(1+B$6)/($A10-B$6)/(1+$A10)^7+DCF!$L$34)/DCF!$L$38 -> 198.9782 | C10: =(DCF!$F$14/(1+$A10)^1+DCF!$G$14/(1+$A10)^2+DCF!$H$14/(1+$A10)^3+DCF!$I$14/(1+$A10)^4+DCF!$J$14/(1+$A10)^5+DCF!$K$14/(1+$A10)^6+DCF!$L$14/(1+$A10)^7+DCF!$L$14*(1+C$6)/($A10-C$6)/(1+$A10)^7+DCF!$L$34)/DCF!$L$38 -> 208.63988 | D10: =(DCF!$F$14/(1+$A10)^1+DCF!$G$14/(1+$A10)^2+DCF!$H$14/(1+$A10)^3+DCF!$I$14/(1+$A10)^4+DCF!$J$14/(1+$A10)^5+DCF!$K$14/(1+$A10)^6+DCF!$L$14/(1+$A10)^7+DCF!$L$14*(1+D$6)/($A10-D$6)/(1+$A10)^7+DCF!$L$34)/DCF!$L$38 -> 219.75224 | E10: =(DCF!$F$14/(1+$A10)^1+DCF!$G$14/(1+$A10)^2+DCF!$H$14/(1+$A10)^3+DCF!$I$14/(1+$A10)^4+DCF!$J$14/(1+$A10)^5+DCF!$K$14/(1+$A10)^6+DCF!$L$14/(1+$A10)^7+DCF!$L$14*(1+E$6)/($A10-E$6)/(1+$A10)^7+DCF!$L$34)/DCF!$L$38 -> 232.6685 | F10: =(DCF!$F$14/(1+$A10)^1+DCF!$G$14/(1+$A10)^2+DCF!$H$14/(1+$A10)^3+DCF!$I$14/(1+$A10)^4+DCF!$J$14/(1+$A10)^5+DCF!$K$14/(1+$A10)^6+DCF!$L$14/(1+$A10)^7+DCF!$L$14*(1+F$6)/($A10-F$6)/(1+$A10)^7+DCF!$L$34)/DCF!$L$38 -> 247.86671
A11: =Assumptions!$D$59+0.01 -> 0.13660169 | B11: =(DCF!$F$14/(1+$A11)^1+DCF!$G$14/(1+$A11)^2+DCF!$H$14/(1+$A11)^3+DCF!$I$14/(1+$A11)^4+DCF!$J$14/(1+$A11)^5+DCF!$K$14/(1+$A11)^6+DCF!$L$14/(1+$A11)^7+DCF!$L$14*(1+B$6)/($A11-B$6)/(1+$A11)^7+DCF!$L$34)/DCF!$L$38 -> 186.38298 | C11: =(DCF!$F$14/(1+$A11)^1+DCF!$G$14/(1+$A11)^2+DCF!$H$14/(1+$A11)^3+DCF!$I$14/(1+$A11)^4+DCF!$J$14/(1+$A11)^5+DCF!$K$14/(1+$A11)^6+DCF!$L$14/(1+$A11)^7+DCF!$L$14*(1+C$6)/($A11-C$6)/(1+$A11)^7+DCF!$L$34)/DCF!$L$38 -> 194.63934 | D11: =(DCF!$F$14/(1+$A11)^1+DCF!$G$14/(1+$A11)^2+DCF!$H$14/(1+$A11)^3+DCF!$I$14/(1+$A11)^4+DCF!$J$14/(1+$A11)^5+DCF!$K$14/(1+$A11)^6+DCF!$L$14/(1+$A11)^7+DCF!$L$14*(1+D$6)/($A11-D$6)/(1+$A11)^7+DCF!$L$34)/DCF!$L$38 -> 204.0488 | E11: =(DCF!$F$14/(1+$A11)^1+DCF!$G$14/(1+$A11)^2+DCF!$H$14/(1+$A11)^3+DCF!$I$14/(1+$A11)^4+DCF!$J$14/(1+$A11)^5+DCF!$K$14/(1+$A11)^6+DCF!$L$14/(1+$A11)^7+DCF!$L$14*(1+E$6)/($A11-E$6)/(1+$A11)^7+DCF!$L$34)/DCF!$L$38 -> 214.87106 | F11: =(DCF!$F$14/(1+$A11)^1+DCF!$G$14/(1+$A11)^2+DCF!$H$14/(1+$A11)^3+DCF!$I$14/(1+$A11)^4+DCF!$J$14/(1+$A11)^5+DCF!$K$14/(1+$A11)^6+DCF!$L$14/(1+$A11)^7+DCF!$L$14*(1+F$6)/($A11-F$6)/(1+$A11)^7+DCF!$L$34)/DCF!$L$38 -> 227.45013
A13: IMPLIED UPSIDE / (DOWNSIDE) vs REFERENCE PRICE
A14: WACC \ g | B14: 0.055 | C14: 0.06 | D14: 0.065 | E14: 0.07 | F14: 0.075
A15: =Assumptions!$D$59+-0.01 -> 0.11660169 | B15: =B7/Assumptions!$D$6-1 -> 0.026488278 | C15: =C7/Assumptions!$D$6-1 -> 0.094282171 | D15: =D7/Assumptions!$D$6-1 -> 0.17521399 | E15: =E7/Assumptions!$D$6-1 -> 0.27351251 | F15: =F7/Assumptions!$D$6-1 -> 0.39543954
A16: =Assumptions!$D$59+-0.005 -> 0.12160169 | B16: =B8/Assumptions!$D$6-1 -> -0.053129409 | C16: =C8/Assumptions!$D$6-1 -> 0.0029614986 | D16: =D8/Assumptions!$D$6-1 -> 0.068962166 | E16: =E8/Assumptions!$D$6-1 -> 0.14775324 | F16: =F8/Assumptions!$D$6-1 -> 0.24345166
A17: =Assumptions!$D$59+0 -> 0.12660169 | B17: =B9/Assumptions!$D$6-1 -> -0.12146123 | C17: =C9/Assumptions!$D$6-1 -> -0.074474917 | D17: =D9/Assumptions!$D$6-1 -> -0.019861165 | E17: =E9/Assumptions!$D$6-1 -> 0.044401371 | F17: =F9/Assumptions!$D$6-1 -> 0.12111748
A18: =Assumptions!$D$59+0.005 -> 0.13160169 | B18: =B10/Assumptions!$D$6-1 -> -0.18072139 | C18: =C10/Assumptions!$D$6-1 -> -0.14094008 | D18: =D10/Assumptions!$D$6-1 -> -0.095185748 | E18: =E10/Assumptions!$D$6-1 -> -0.042003967 | F18: =F10/Assumptions!$D$6-1 -> 0.020573608
A19: =Assumptions!$D$59+0.01 -> 0.13660169 | B19: =B11/Assumptions!$D$6-1 -> -0.2325813 | C19: =C11/Assumptions!$D$6-1 -> -0.19858631 | D19: =D11/Assumptions!$D$6-1 -> -0.15984352 | E19: =E11/Assumptions!$D$6-1 -> -0.11528364 | F19: =F11/Assumptions!$D$6-1 -> -0.063490221

Sheet DCF
B2: Discounted Cash Flow - FCFF
B3: Valuation date 31 March 2026. FY27E-FY33E discounted at periods 1 to 7. A seven-year explicit forecast is used because the business is still scaling and near-term free cash flow is not representative.
A5: # | B5: Free cash flow to the firm (₹ cr) | C5: Units | D5: FY25A | E5: FY26E | F5: FY27E | G5: FY28E | H5: FY29E | I5: FY30E | J5: FY31E | K5: FY32E | L5: FY33E
B6: FCFF BUILD
B7: EBIT | C7: ₹ cr | F7: =Model!F26 -> 2740.7282 | G7: =Model!G26 -> 6472.5325 | H7: =Model!H26 -> 10833.328 | I7: =Model!I26 -> 15687.15 | J7: =Model!J26 -> 19967.419 | K7: =Model!K26 -> 24083.356 | L7: =Model!L26 -> 27730.329
B8: Effective tax rate | C8: % | F8: =Assumptions!F56 -> 0.32 | G8: =Assumptions!G56 -> 0.24 | H8: =Assumptions!H56 -> 0.2 | I8: =Assumptions!I56 -> 0.22 | J8: =Assumptions!J56 -> 0.2517 | K8: =Assumptions!K56 -> 0.2517 | L8: =Assumptions!L56 -> 0.2517
B9: NOPAT | F9: =F7*(1-F8) -> 1863.6952 | G9: =G7*(1-G8) -> 4919.1247 | H9: =H7*(1-H8) -> 8666.6627 | I9: =I7*(1-I8) -> 12235.977 | J9: =J7*(1-J8) -> 14941.619 | K9: =K7*(1-K8) -> 18021.575 | L9: =L7*(1-L8) -> 20750.605
B10: Add: depreciation & amortisation | F10: =-Model!F24 -> 1914.927 | G10: =-Model!G24 -> 2368.6687 | H10: =-Model!H24 -> 2901.9657 | I10: =-Model!I24 -> 3453.1381 | J10: =-Model!J24 -> 4010.7532 | K10: =-Model!K24 -> 4577.4458 | L10: =-Model!L24 -> 5133.8389
B11: Less: capital expenditure | F11: =Model!F78 -> -1509.3691 | G11: =Model!G78 -> -1779.6486 | H11: =Model!H78 -> -1989.3293 | I11: =Model!I78 -> -2203.2161 | J11: =Model!J78 -> -2384.5524 | K11: =Model!K78 -> -2549.4782 | L11: =Model!L78 -> -2692.7428
B12: Less: increase in net working capital | F12: =SUM(Model!F70:F76) -> 1770.1626 | G12: =SUM(Model!G70:G76) -> 1554.9465 | H12: =SUM(Model!H70:H76) -> 1699.3774 | I12: =SUM(Model!I70:I76) -> 1738.2201 | J12: =SUM(Model!J70:J76) -> 1694.914 | K12: =SUM(Model!K70:K76) -> 1607.5529 | L12: =SUM(Model!L70:L76) -> 1484.7094
B13: Less: lease principal repayments | F13: =Model!F80 -> -893.26 | G13: =Model!G80 -> -1231.805 | H13: =Model!H80 -> -1614.42 | I13: =Model!I80 -> -2007.78 | J13: =Model!J80 -> -2402.785 | K13: =Model!K80 -> -2806.08 | L13: =Model!L80 -> -3200.51
B14: FREE CASH FLOW TO THE FIRM | F14: =SUM(F9:F13) -> 3146.1557 | G14: =SUM(G9:G13) -> 5831.2864 | H14: =SUM(H9:H13) -> 9664.2564 | I14: =SUM(I9:I13) -> 13216.339 | J14: =SUM(J9:J13) -> 15859.949 | K14: =SUM(K9:K13) -> 18851.015 | L14: =SUM(L9:L13) -> 21475.901
B15: FCFF margin on B2C net order value | F15: =F14/RevBuild!F43 -> 0.022567809 | G15: =G14/RevBuild!G43 -> 0.030915678 | H15: =H14/RevBuild!H43 -> 0.039937704 | I15: =I14/RevBuild!I43 -> 0.044564474 | J15: =J14/RevBuild!J43 -> 0.045332616 | K15: =K14/RevBuild!K43 -> 0.04699545 | L15: =L14/RevBuild!L43 -> 0.04783566
A18: # | B18: DISCOUNTING
B19: Discount period | C19: yrs | F19: 1 | G19: 2 | H19: 3 | I19: 4 | J19: 5 | K19: 6 | L19: 7
B20: WACC | F20: =Assumptions!$D$59 -> 0.12660169 | G20: =Assumptions!$D$59 -> 0.12660169 | H20: =Assumptions!$D$59 -> 0.12660169 | I20: =Assumptions!$D$59 -> 0.12660169 | J20: =Assumptions!$D$59 -> 0.12660169 | K20: =Assumptions!$D$59 -> 0.12660169 | L20: =Assumptions!$D$59 -> 0.12660169
B21: Discount factor | F21: =1/(1+F20)^F19 -> 0.88762516 | G21: =1/(1+G20)^G19 -> 0.78787842 | H21: =1/(1+H20)^H19 -> 0.69934071 | I21: =1/(1+I20)^I19 -> 0.62075241 | J21: =1/(1+J20)^J19 -> 0.55099545 | K21: =1/(1+K20)^K19 -> 0.48907743 | L21: =1/(1+L20)^L19 -> 0.43411743
B22: PV of FCFF | F22: =F14*F21 -> 2792.6069 | G22: =G14*G21 -> 4594.3447 | H22: =H14*H21 -> 6758.608 | I22: =I14*I21 -> 8204.0742 | J22: =J14*J21 -> 8738.7599 | K22: =K14*K21 -> 9219.6062 | L22: =L14*L21 -> 9323.0629
A24: # | B24: ENTERPRISE & EQUITY VALUE
B25: PV of explicit forecast FCFF (FY27E-FY33E) | C25: ₹ cr | L25: =SUM(F22:L22) -> 49631.063
B26: Terminal growth rate (INR nominal) | L26: =Assumptions!$D$60 -> 0.065
B27: Terminal value at FY33E (Gordon growth) | C27: ₹ cr | L27: =L14*(1+L26)/(L20-L26) -> 371285.85
B28: PV of terminal value | C28: ₹ cr | L28: =L27*L21 -> 161181.66
B29: ENTERPRISE VALUE | C29: ₹ cr | L29: =L25+L28 -> 210812.72
B30: Terminal value as % of enterprise value | L30: =L28/L29 -> 0.76457274
B32: Cash, deposits & treasury investments, FY26E | C32: ₹ cr | L32: =Model!E36 -> 23601.497
B33: Less: lease liabilities, FY26E | C33: ₹ cr | L33: =-Model!E50 -> -4690
B34: Net cash after lease liabilities | C34: ₹ cr | L34: =L32+L33 -> 18911.497
A36: # | B36: EQUITY VALUE | C36: ₹ cr | L36: =L29+L34 -> 229724.22
B38: Shares outstanding (crore) | L38: =Assumptions!$D$7 -> 965.04
A40: # | B40: VALUE PER SHARE - DCF | C40: ₹/sh | L40: =L36/L38 -> 238.04632
B41: Current market price | C41: ₹/sh | L41: =Assumptions!$D$6 -> 242.87
B42: Implied upside / (downside) | L42: =L40/L41-1 -> -0.019861165
A45: # | B45: REVERSE DCF - WHAT THE CURRENT PRICE IMPLIES
B46: Market capitalisation at CMP | L46: =Assumptions!$D$8 -> 234379.26
B47: Less: net cash after lease liabilities | L47: =-L34 -> -18911.497
B48: Market-implied enterprise value | L48: =L46+L47 -> 215467.77
B49: Less: PV of explicit FY27E-FY33E FCFF | L49: =-L25 -> -49631.063
B50: Market-implied PV of terminal value | L50: =L48+L49 -> 165836.71
B51: Market-implied terminal value at FY33E | L51: =L50/L21 -> 382008.86
B52: IMPLIED PERPETUAL GROWTH AT CURRENT PRICE | L52: =(L51*L20-L14)/(L51+L14) -> 0.066637126
B53: Our base-case terminal growth | L53: =Assumptions!$D$60 -> 0.065
B54: India nominal GDP growth (reference) | L54: 0.105

Sheet SOTP
B2: Sum-of-the-Parts - FY30E Segment Metrics
B3: Eternal is four businesses with different growth, margin and capital profiles. Consolidated multiples are close to meaningless here; this is the primary valuation method.
A5: # | B5: Segment | C5: Valuation metric (FY30E) | D5: Metric value (₹ cr) | E5: Multiple | F5: Enterprise value (₹ cr) | G5: % of total
B6: Quick commerce (Blinkit) | C6: EV / net order value | D6: =RevBuild!I12 -> 200312 | E6: 1.5 | F6: =D6*E6 -> 300468 | G6: =F6/$F$11 -> 0.6107083
B7: Food delivery (Zomato) | C7: EV / adjusted EBITDA | D7: =RevBuild!I25 -> 4837.3235 | E7: 30 | F7: =D7*E7 -> 145119.7 | G7: =F7/$F$11 -> 0.29495922
B8: Going-out (District) | C8: EV / net order value | D8: =RevBuild!I28 -> 28123.381 | E8: 1 | F8: =D8*E8 -> 28123.381 | G8: =F8/$F$11 -> 0.057161436
B9: Hyperpure (B2B supplies) | C9: EV / revenue | D9: =RevBuild!I31 -> 12192.082 | E9: 1.5 | F9: =D9*E9 -> 18288.123 | G9: =F9/$F$11 -> 0.037171042
B10: Other segments (Bistro, Nugget) | C10: Loss-making; no value ascribed | D10: =RevBuild!I33 -> 1500 | E10: 0 | F10: =D10*E10 -> 0 | G10: =F10/$F$11 -> 0
B11: Total enterprise value, FY30E basis | F11: =SUM(F6:F10) -> 491999.21
A13: # | B13: DISCOUNT BACK TO THE VALUATION DATE
B14: Years from 31-Mar-2026 to FY30E | D14: 4
B15: Discount rate (WACC) | D15: =Assumptions!$D$59 -> 0.12660169
B16: Discount factor | D16: =1/(1+D15)^D14 -> 0.62075241
B17: Present value of segment enterprise value | D17: =F11*D16 -> 305409.69
B19: Add: net cash after lease liabilities, FY26E | D19: =DCF!L34 -> 18911.497
B20: EQUITY VALUE | D20: =D17+D19 -> 324321.19
B22: Shares outstanding (crore) | D22: =Assumptions!$D$7 -> 965.04
B24: VALUE PER SHARE - SOTP | D24: =D20/D22 -> 336.0702
B25: Implied upside / (downside) | D25: =D24/Assumptions!$D$6-1 -> 0.38374523
A27: # | B27: CROSS-CHECK - WHAT EACH MULTIPLE IMPLIES
B28: Blinkit EV / FY30E revenue (implied) | D28: =F6/RevBuild!I15 -> 1.6304348
B29: Blinkit EV / FY30E adjusted EBITDA (implied) | D29: =F6/RevBuild!I17 -> 29.411765
B30: Food delivery EV / FY30E NOV (implied) | D30: =F7/RevBuild!I20 -> 2.13
B31: DMart EV / trailing revenue (reference) | D31: =Comps!H7 -> 3.5333837
B32: Blinkit implied EV as % of total | D32: =G6 -> 0.6107083

Sheet Comps
B2: Listed Peer Comparables - India Consumer Internet & Organised Retail
B3: Prices as at the dates stated below. Every figure sourced; none carried from memory. The peer set is deliberately narrow - see the note.
A5: # | B5: Company | C5: Price (₹) | D5: Mkt cap (₹ cr) | E5: Net cash (₹ cr) | F5: Ent. value (₹ cr) | G5: Revenue (₹ cr) | H5: EV / revenue | I5: EBITDA margin | J5: Revenue growth
B6: Swiggy Limited | C6: 302 | D6: 83352 | E6: 15500 | F6: =D6-E6 -> 67852 | G6: 21081 | H6: =F6/G6 -> 3.2186329 | I6: -0.155 | J6: 0.52
B7: Avenue Supermarts (DMart) | C7: 3783 | D7: 246171 | E7: 3000 | F7: =D7-E7 -> 243171 | G7: 68821 | H7: =F7/G7 -> 3.5333837 | I7: 0.08 | J7: 0.16
B8: Zepto (unlisted, IPO-bound) - last private mark | D8: 63000
B9: ETERNAL (this model, FY26E) | C9: =Assumptions!$D$6 -> 242.87 | D9: =Assumptions!$D$8 -> 234379.26 | E9: =Model!E94 -> 18911.497 | F9: =D9-E9 -> 215467.77 | G9: =Model!E7 -> 54670.182 | H9: =F9/G9 -> 3.9412301 | I9: =Model!E23/Model!E7 -> 0.024820382 | J9: =Model!E8 -> 1.7008651
B10: Eternal premium / (discount) to DMart on EV / revenue | H10: =H9/H7-1 -> 0.11542658
A12: # | B12: WHY EV / REVENUE DOES NOT WORK HERE - AND WHAT DOES
B13: Eternal EV / FY27E B2C net order value | D13: =F9/RevBuild!F43 -> 1.54558
B14: Swiggy EV / FY27E gross order value (estimate) | D14: =F6/78000 -> 0.86989744
B15: Eternal premium to Swiggy on EV / order value | D15: =D13/D14-1 -> 0.77673824
A17: # | B17: IMPLIED VALUATION - EV / NET ORDER VALUE
B18: FY27E B2C net order value (₹ cr) | D18: =RevBuild!F43 -> 139409
B19: Target EV / NOV multiple | D19: 2.1
B20: Implied enterprise value (₹ cr) | D20: =D18*D19 -> 292758.9
B21: Add: net cash after lease liabilities, FY26E (₹ cr) | D21: =Model!E94 -> 18911.497
B22: Implied value per share - EV / NOV method | D22: =(D20+D21)/Assumptions!$D$7 -> 322.96112

Sheet Scenarios
B1: ADITYA NAIR RESEARCH
B2: Scenarios - Bull / Base / Bear
B3: Each scenario is a live seven-year mini-DCF driven off Blinkit's store count, store productivity and margin - the three variables that decide this stock. Assumption deltas are stated, not just outputs.
A5: # | B5: Scenario driver | C5: Units | D5: FY27E | E5: FY28E | F5: FY29E | G5: FY30E | H5: FY31E | I5: FY32E | J5: FY33E | K5: Value/sh
A6: # | B6: BULL - competition rationalises, Blinkit runs at 4,000 stores by March 2027 and lands the top of its guided margin band
B7: Blinkit dark stores, closing | C7: count | D7: 3600 | E7: 4900 | F7: 6200 | G7: 7300 | H7: 8200 | I7: 9000 | J7: 9600
B8: NOV per store per day | C8: ₹ lakh | D8: 8.9 | E8: 9.9 | F8: 10.9 | G8: 11.8 | H8: 12.6 | I8: 13.3 | J8: 13.9
B9: Blinkit net order value | C9: ₹ cr | D9: =(Assumptions!$E$14+D7)/2*365*D8/100 -> 95830.75 | E9: =(D7+E7)/2*365*E8/100 -> 153573.75 | F9: =(E7+F7)/2*365*F8/100 -> 220806.75 | G9: =(F7+G7)/2*365*G8/100 -> 290722.5 | H9: =(G7+H7)/2*365*H8/100 -> 356422.5 | I9: =(H7+I7)/2*365*I8/100 -> 417487 | J9: =(I7+J7)/2*365*J8/100 -> 471835.5
B10: Blinkit adjusted EBITDA margin (% of NOV) | C10: % | D10: 0.024 | E10: 0.04 | F10: 0.052 | G10: 0.059 | H10: 0.063 | I10: 0.065 | J10: 0.065
B11: Consolidated adjusted EBITDA | C11: ₹ cr | D11: =D9*D10+(RevBuild!F45-RevBuild!F17) -> 4670.2332 | E11: =E9*E10+(RevBuild!G45-RevBuild!G17) -> 9789.9212 | F11: =F9*F10+(RevBuild!H45-RevBuild!H17) -> 16518.168 | G11: =G9*G10+(RevBuild!I45-RevBuild!I17) -> 23833.803 | H11: =H9*H10+(RevBuild!J45-RevBuild!J17) -> 30425.959 | I11: =I9*I10+(RevBuild!K45-RevBuild!K17) -> 36326.651 | J11: =J9*J10+(RevBuild!L45-RevBuild!L17) -> 40891.273
B12: Free cash flow to the firm | C12: ₹ cr | D12: =DCF!F14*D11/RevBuild!F45 -> 3687.0959 | E12: =DCF!G14*E11/RevBuild!G45 -> 7457.1969 | F12: =DCF!H14*F11/RevBuild!H45 -> 13284.945 | G12: =DCF!I14*G11/RevBuild!I45 -> 18642.007 | H12: =DCF!J14*H11/RevBuild!J45 -> 22731.032 | I12: =DCF!K14*I11/RevBuild!K45 -> 26942.582 | J12: =DCF!L14*J11/RevBuild!L45 -> 30122.038
B13: WACC / terminal growth | D13: 0.116 | E13: 0.07 | K13: =(D12/(1+$D$13)^1+E12/(1+$D$13)^2+F12/(1+$D$13)^3+G12/(1+$D$13)^4+H12/(1+$D$13)^5+I12/(1+$D$13)^6+J12/(1+$D$13)^7+J12*(1+$E$13)/($D$13-$E$13)/(1+$D$13)^7+DCF!$L$34)/DCF!$L$38 -> 430.87394
B14: Implied upside / (downside) vs reference price | K14: =K13/Assumptions!$D$6-1 -> 0.77409288
A16: # | B16: BASE - mirrors the main model; drivers linked live to the Assumptions tab
B17: Blinkit dark stores, closing | C17: count | D17: =Assumptions!F14 -> 3300 | E17: =Assumptions!G14 -> 4300 | F17: =Assumptions!H14 -> 5200 | G17: =Assumptions!I14 -> 6000 | H17: =Assumptions!J14 -> 6700 | I17: =Assumptions!K14 -> 7300 | J17: =Assumptions!L14 -> 7800
B18: NOV per store per day | C18: ₹ lakh | D18: =Assumptions!F15 -> 7.9 | E18: =Assumptions!G15 -> 8.5 | F18: =Assumptions!H15 -> 9.15 | G18: =Assumptions!I15 -> 9.8 | H18: =Assumptions!J15 -> 10.4 | I18: =Assumptions!K15 -> 10.95 | J18: =Assumptions!L15 -> 11.45
B19: Blinkit net order value | C19: ₹ cr | D19: =(Assumptions!$E$14+D17)/2*365*D18/100 -> 80738 | E19: =(D17+E17)/2*365*E18/100 -> 117895 | F19: =(E17+F17)/2*365*F18/100 -> 158638.12 | G19: =(F17+G17)/2*365*G18/100 -> 200312 | H19: =(G17+H17)/2*365*H18/100 -> 241046 | I19: =(H17+I17)/2*365*I18/100 -> 279772.5 | J19: =(I17+J17)/2*365*J18/100 -> 315533.37
B20: Blinkit adjusted EBITDA margin (% of NOV) | C20: % | D20: =Assumptions!F17 -> 0.02 | E20: =Assumptions!G17 -> 0.034 | F20: =Assumptions!H17 -> 0.044 | G20: =Assumptions!I17 -> 0.051 | H20: =Assumptions!J17 -> 0.055 | I20: =Assumptions!K17 -> 0.058 | J20: =Assumptions!L17 -> 0.06
B21: Consolidated adjusted EBITDA | C21: ₹ cr | D21: =D19*D20+(RevBuild!F45-RevBuild!F17) -> 3985.0552 | E21: =E19*E20+(RevBuild!G45-RevBuild!G17) -> 7655.4012 | F21: =F19*F20+(RevBuild!H45-RevBuild!H17) -> 12016.294 | G21: =G19*G20+(RevBuild!I45-RevBuild!I17) -> 16897.088 | H21: =H19*H20+(RevBuild!J45-RevBuild!J17) -> 21228.872 | I21: =I19*I20+(RevBuild!K45-RevBuild!K17) -> 25416.801 | J21: =J19*J20+(RevBuild!L45-RevBuild!L17) -> 29153.968
B22: Free cash flow to the firm | C22: ₹ cr | D22: =DCF!F14*D21/RevBuild!F45 -> 3146.1557 | E22: =DCF!G14*E21/RevBuild!G45 -> 5831.2864 | F22: =DCF!H14*F21/RevBuild!H45 -> 9664.2564 | G22: =DCF!I14*G21/RevBuild!I45 -> 13216.339 | H22: =DCF!J14*H21/RevBuild!J45 -> 15859.949 | I22: =DCF!K14*I21/RevBuild!K45 -> 18851.015 | J22: =DCF!L14*J21/RevBuild!L45 -> 21475.901
B23: WACC / terminal growth | D23: =Assumptions!$D$59 -> 0.12660169 | E23: =Assumptions!$D$60 -> 0.065 | K23: =(D22/(1+$D$23)^1+E22/(1+$D$23)^2+F22/(1+$D$23)^3+G22/(1+$D$23)^4+H22/(1+$D$23)^5+I22/(1+$D$23)^6+J22/(1+$D$23)^7+J22*(1+$E$23)/($D$23-$E$23)/(1+$D$23)^7+DCF!$L$34)/DCF!$L$38 -> 238.04632
B24: Implied upside / (downside) vs reference price | K24: =K23/Assumptions!$D$6-1 -> -0.019861165
A26: # | B26: BEAR - Amazon Now, Flipkart Minutes and a freshly funded Zepto turn quick commerce into a multi-year subsidy war
B27: Blinkit dark stores, closing | C27: count | D27: 3000 | E27: 3600 | F27: 4100 | G27: 4500 | H27: 4800 | I27: 5000 | J27: 5150
B28: NOV per store per day | C28: ₹ lakh | D28: 8.2 | E28: 8.4 | F28: 8.7 | G28: 9 | H28: 9.3 | I28: 9.55 | J28: 9.8
B29: Blinkit net order value | C29: ₹ cr | D29: =(Assumptions!$E$14+D27)/2*365*D28/100 -> 79314.5 | E29: =(D27+E27)/2*365*E28/100 -> 101178 | F29: =(E27+F27)/2*365*F28/100 -> 122256.75 | G29: =(F27+G27)/2*365*G28/100 -> 141255 | H29: =(G27+H27)/2*365*H28/100 -> 157844.25 | I29: =(H27+I27)/2*365*I28/100 -> 170801.75 | J29: =(I27+J27)/2*365*J28/100 -> 181532.75
B30: Blinkit adjusted EBITDA margin (% of NOV) | C30: % | D30: 0.008 | E30: 0.015 | F30: 0.022 | G30: 0.028 | H30: 0.032 | I30: 0.035 | J30: 0.036
B31: Consolidated adjusted EBITDA | C31: ₹ cr | D31: =D29*D30+(RevBuild!F45-RevBuild!F17) -> 3004.8112 | E31: =E29*E30+(RevBuild!G45-RevBuild!G17) -> 5164.6412 | F31: =F29*F30+(RevBuild!H45-RevBuild!H17) -> 7725.8651 | G31: =G29*G30+(RevBuild!I45-RevBuild!I17) -> 10636.316 | H31: =H29*H30+(RevBuild!J45-RevBuild!J17) -> 13022.358 | I31: =I29*I30+(RevBuild!K45-RevBuild!K17) -> 15168.058 | J31: =J29*J30+(RevBuild!L45-RevBuild!L17) -> 16757.145
B32: Free cash flow to the firm | C32: ₹ cr | D32: =DCF!F14*D31/RevBuild!F45 -> 2372.2642 | E32: =DCF!G14*E31/RevBuild!G45 -> 3934.02 | F32: =DCF!H14*F31/RevBuild!H45 -> 6213.6247 | G32: =DCF!I14*G31/RevBuild!I45 -> 8319.3717 | H32: =DCF!J14*H31/RevBuild!J45 -> 9728.917 | I32: =DCF!K14*I31/RevBuild!K45 -> 11249.775 | J32: =DCF!L14*J31/RevBuild!L45 -> 12343.938
B33: WACC / terminal growth | D33: 0.136 | E33: 0.06 | K33: =(D32/(1+$D$33)^1+E32/(1+$D$33)^2+F32/(1+$D$33)^3+G32/(1+$D$33)^4+H32/(1+$D$33)^5+I32/(1+$D$33)^6+J32/(1+$D$33)^7+J32*(1+$E$33)/($D$33-$E$33)/(1+$D$33)^7+DCF!$L$34)/DCF!$L$38 -> 123.55213
B34: Implied upside / (downside) vs reference price | K34: =K33/Assumptions!$D$6-1 -> -0.49128288
A36: # | B36: SCENARIO SUMMARY
D37: Value/share | E37: Upside | F37: Probability | G37: Weighted
B38: Bull | D38: =K13 -> 430.87394 | E38: =D38/Assumptions!$D$6-1 -> 0.77409288 | F38: 0.25 | G38: =D38*F38 -> 107.71848
B39: Base | D39: =K23 -> 238.04632 | E39: =D39/Assumptions!$D$6-1 -> -0.019861165 | F39: 0.5 | G39: =D39*F39 -> 119.02316
B40: Bear | D40: =K33 -> 123.55213 | E40: =D40/Assumptions!$D$6-1 -> -0.49128288 | F40: 0.25 | G40: =D40*F40 -> 30.888032
B41: Probability-weighted value per share | G41: =SUM(G38:G40) -> 257.62968
B42: Probability check (must equal 100%) | F42: =SUM(F38:F40) -> 1
